{
  "count": 7,
  "similarityRate": 0.24265553902036377,
  "trials": [
    {
      "id": "Prompt_Wranglers_J_2.png",
      "label": "J",
      "similarity": 0.018123643472790718
    },
    {
      "id": "Prompt_Wranglers_J_3.png",
      "label": "J",
      "similarity": 0.0008101117564365268
    },
    {
      "id": "Prompt_Wranglers_J_4.png",
      "label": "J",
      "similarity": 0.002402364043518901
    },
    {
      "id": "Prompt_Wranglers_J_5.png",
      "label": "J",
      "similarity": 0.000786866876296699
    },
    {
      "id": "Prompt_Wranglers_J_6.png",
      "label": "J",
      "similarity": 0.03862813860177994
    },
    {
      "id": "Prompt_Wranglers_J_8.png",
      "label": "J",
      "similarity": 0.8239127397537231
    },
    {
      "id": "Prompt_Wranglers_J_9.png",
      "label": "J",
      "similarity": 0.8139249086380005
    }
  ],
  "similarities": [
    {
      "id": "Prompt_Wranglers_J_2.png",
      "raws": [
        {
          "id": "Prompt_Wranglers_J_2.png",
          "label": "A",
          "softmax_prob": 0.009836969897150993
        },
        {
          "id": "Prompt_Wranglers_J_2.png",
          "label": "B",
          "softmax_prob": 0.008379964157938957
        },
        {
          "id": "Prompt_Wranglers_J_2.png",
          "label": "C",
          "softmax_prob": 0.012888471595942974
        },
        {
          "id": "Prompt_Wranglers_J_2.png",
          "label": "D",
          "softmax_prob": 0.01717963255941868
        },
        {
          "id": "Prompt_Wranglers_J_2.png",
          "label": "E",
          "softmax_prob": 0.006519251503050327
        },
        {
          "id": "Prompt_Wranglers_J_2.png",
          "label": "F",
          "softmax_prob": 0.01870829239487648
        },
        {
          "id": "Prompt_Wranglers_J_2.png",
          "label": "G",
          "softmax_prob": 0.010351156815886497
        },
        {
          "id": "Prompt_Wranglers_J_2.png",
          "label": "H",
          "softmax_prob": 0.011395234614610672
        },
        {
          "id": "Prompt_Wranglers_J_2.png",
          "label": "I",
          "softmax_prob": 0.21228183805942535
        },
        {
          "id": "Prompt_Wranglers_J_2.png",
          "label": "J",
          "softmax_prob": 0.018123643472790718
        },
        {
          "id": "Prompt_Wranglers_J_2.png",
          "label": "K",
          "softmax_prob": 0.013583814725279808
        },
        {
          "id": "Prompt_Wranglers_J_2.png",
          "label": "L",
          "softmax_prob": 0.4491634964942932
        },
        {
          "id": "Prompt_Wranglers_J_2.png",
          "label": "M",
          "softmax_prob": 0.007596897426992655
        },
        {
          "id": "Prompt_Wranglers_J_2.png",
          "label": "N",
          "softmax_prob": 0.005463884677737951
        },
        {
          "id": "Prompt_Wranglers_J_2.png",
          "label": "O",
          "softmax_prob": 0.014388254843652248
        },
        {
          "id": "Prompt_Wranglers_J_2.png",
          "label": "P",
          "softmax_prob": 0.009851096197962761
        },
        {
          "id": "Prompt_Wranglers_J_2.png",
          "label": "Q",
          "softmax_prob": 0.005826123524457216
        },
        {
          "id": "Prompt_Wranglers_J_2.png",
          "label": "R",
          "softmax_prob": 0.004838862456381321
        },
        {
          "id": "Prompt_Wranglers_J_2.png",
          "label": "S",
          "softmax_prob": 0.020348992198705673
        },
        {
          "id": "Prompt_Wranglers_J_2.png",
          "label": "T",
          "softmax_prob": 0.02726513147354126
        },
        {
          "id": "Prompt_Wranglers_J_2.png",
          "label": "U",
          "softmax_prob": 0.006790469866245985
        },
        {
          "id": "Prompt_Wranglers_J_2.png",
          "label": "V",
          "softmax_prob": 0.010791405104100704
        },
        {
          "id": "Prompt_Wranglers_J_2.png",
          "label": "W",
          "softmax_prob": 0.007075062487274408
        },
        {
          "id": "Prompt_Wranglers_J_2.png",
          "label": "X",
          "softmax_prob": 0.020111141726374626
        },
        {
          "id": "Prompt_Wranglers_J_2.png",
          "label": "Y",
          "softmax_prob": 0.05606803670525551
        },
        {
          "id": "Prompt_Wranglers_J_2.png",
          "label": "Z",
          "softmax_prob": 0.015172860585153103
        }
      ]
    },
    {
      "id": "Prompt_Wranglers_J_3.png",
      "raws": [
        {
          "id": "Prompt_Wranglers_J_3.png",
          "label": "A",
          "softmax_prob": 0.0004194968205410987
        },
        {
          "id": "Prompt_Wranglers_J_3.png",
          "label": "B",
          "softmax_prob": 0.00021298279170878232
        },
        {
          "id": "Prompt_Wranglers_J_3.png",
          "label": "C",
          "softmax_prob": 0.0002991886285599321
        },
        {
          "id": "Prompt_Wranglers_J_3.png",
          "label": "D",
          "softmax_prob": 0.00015064033505041152
        },
        {
          "id": "Prompt_Wranglers_J_3.png",
          "label": "E",
          "softmax_prob": 0.0002448372542858124
        },
        {
          "id": "Prompt_Wranglers_J_3.png",
          "label": "F",
          "softmax_prob": 0.0004563354596029967
        },
        {
          "id": "Prompt_Wranglers_J_3.png",
          "label": "G",
          "softmax_prob": 0.0006466555641964078
        },
        {
          "id": "Prompt_Wranglers_J_3.png",
          "label": "H",
          "softmax_prob": 0.9876022934913635
        },
        {
          "id": "Prompt_Wranglers_J_3.png",
          "label": "I",
          "softmax_prob": 0.0011253022821620107
        },
        {
          "id": "Prompt_Wranglers_J_3.png",
          "label": "J",
          "softmax_prob": 0.0008101117564365268
        },
        {
          "id": "Prompt_Wranglers_J_3.png",
          "label": "K",
          "softmax_prob": 0.0008197440183721483
        },
        {
          "id": "Prompt_Wranglers_J_3.png",
          "label": "L",
          "softmax_prob": 0.0024793273769319057
        },
        {
          "id": "Prompt_Wranglers_J_3.png",
          "label": "M",
          "softmax_prob": 0.0006580527406185865
        },
        {
          "id": "Prompt_Wranglers_J_3.png",
          "label": "N",
          "softmax_prob": 0.0002602553286124021
        },
        {
          "id": "Prompt_Wranglers_J_3.png",
          "label": "O",
          "softmax_prob": 0.00024039929849095643
        },
        {
          "id": "Prompt_Wranglers_J_3.png",
          "label": "P",
          "softmax_prob": 0.0008106941822916269
        },
        {
          "id": "Prompt_Wranglers_J_3.png",
          "label": "Q",
          "softmax_prob": 0.00011931789777008817
        },
        {
          "id": "Prompt_Wranglers_J_3.png",
          "label": "R",
          "softmax_prob": 0.00016071174468379468
        },
        {
          "id": "Prompt_Wranglers_J_3.png",
          "label": "S",
          "softmax_prob": 0.000730454979930073
        },
        {
          "id": "Prompt_Wranglers_J_3.png",
          "label": "T",
          "softmax_prob": 0.0001953677856363356
        },
        {
          "id": "Prompt_Wranglers_J_3.png",
          "label": "U",
          "softmax_prob": 0.00013068401312921196
        },
        {
          "id": "Prompt_Wranglers_J_3.png",
          "label": "V",
          "softmax_prob": 0.00012793362839147449
        },
        {
          "id": "Prompt_Wranglers_J_3.png",
          "label": "W",
          "softmax_prob": 0.0006885457551106811
        },
        {
          "id": "Prompt_Wranglers_J_3.png",
          "label": "X",
          "softmax_prob": 0.00017524216673336923
        },
        {
          "id": "Prompt_Wranglers_J_3.png",
          "label": "Y",
          "softmax_prob": 0.00020175596000626683
        },
        {
          "id": "Prompt_Wranglers_J_3.png",
          "label": "Z",
          "softmax_prob": 0.0002336959878448397
        }
      ]
    },
    {
      "id": "Prompt_Wranglers_J_4.png",
      "raws": [
        {
          "id": "Prompt_Wranglers_J_4.png",
          "label": "A",
          "softmax_prob": 0.006973176263272762
        },
        {
          "id": "Prompt_Wranglers_J_4.png",
          "label": "B",
          "softmax_prob": 0.059634916484355927
        },
        {
          "id": "Prompt_Wranglers_J_4.png",
          "label": "C",
          "softmax_prob": 0.0019451393745839596
        },
        {
          "id": "Prompt_Wranglers_J_4.png",
          "label": "D",
          "softmax_prob": 0.756100058555603
        },
        {
          "id": "Prompt_Wranglers_J_4.png",
          "label": "E",
          "softmax_prob": 0.001490349997766316
        },
        {
          "id": "Prompt_Wranglers_J_4.png",
          "label": "F",
          "softmax_prob": 0.011629284359514713
        },
        {
          "id": "Prompt_Wranglers_J_4.png",
          "label": "G",
          "softmax_prob": 0.0005916836089454591
        },
        {
          "id": "Prompt_Wranglers_J_4.png",
          "label": "H",
          "softmax_prob": 0.004139610566198826
        },
        {
          "id": "Prompt_Wranglers_J_4.png",
          "label": "I",
          "softmax_prob": 0.01079544797539711
        },
        {
          "id": "Prompt_Wranglers_J_4.png",
          "label": "J",
          "softmax_prob": 0.002402364043518901
        },
        {
          "id": "Prompt_Wranglers_J_4.png",
          "label": "K",
          "softmax_prob": 0.0009472825331613421
        },
        {
          "id": "Prompt_Wranglers_J_4.png",
          "label": "L",
          "softmax_prob": 0.004137485288083553
        },
        {
          "id": "Prompt_Wranglers_J_4.png",
          "label": "M",
          "softmax_prob": 0.003772105323150754
        },
        {
          "id": "Prompt_Wranglers_J_4.png",
          "label": "N",
          "softmax_prob": 0.002984406426548958
        },
        {
          "id": "Prompt_Wranglers_J_4.png",
          "label": "O",
          "softmax_prob": 0.052090249955654144
        },
        {
          "id": "Prompt_Wranglers_J_4.png",
          "label": "P",
          "softmax_prob": 0.008073462173342705
        },
        {
          "id": "Prompt_Wranglers_J_4.png",
          "label": "Q",
          "softmax_prob": 0.004201012197881937
        },
        {
          "id": "Prompt_Wranglers_J_4.png",
          "label": "R",
          "softmax_prob": 0.004064219072461128
        },
        {
          "id": "Prompt_Wranglers_J_4.png",
          "label": "S",
          "softmax_prob": 0.0019527850672602654
        },
        {
          "id": "Prompt_Wranglers_J_4.png",
          "label": "T",
          "softmax_prob": 0.003101797541603446
        },
        {
          "id": "Prompt_Wranglers_J_4.png",
          "label": "U",
          "softmax_prob": 0.008306815288960934
        },
        {
          "id": "Prompt_Wranglers_J_4.png",
          "label": "V",
          "softmax_prob": 0.00909513607621193
        },
        {
          "id": "Prompt_Wranglers_J_4.png",
          "label": "W",
          "softmax_prob": 0.0018821355188265443
        },
        {
          "id": "Prompt_Wranglers_J_4.png",
          "label": "X",
          "softmax_prob": 0.0038557788357138634
        },
        {
          "id": "Prompt_Wranglers_J_4.png",
          "label": "Y",
          "softmax_prob": 0.0022823414765298367
        },
        {
          "id": "Prompt_Wranglers_J_4.png",
          "label": "Z",
          "softmax_prob": 0.03355103358626366
        }
      ]
    },
    {
      "id": "Prompt_Wranglers_J_5.png",
      "raws": [
        {
          "id": "Prompt_Wranglers_J_5.png",
          "label": "A",
          "softmax_prob": 0.00010058768384624273
        },
        {
          "id": "Prompt_Wranglers_J_5.png",
          "label": "B",
          "softmax_prob": 0.0001283305900869891
        },
        {
          "id": "Prompt_Wranglers_J_5.png",
          "label": "C",
          "softmax_prob": 0.00015096990682650357
        },
        {
          "id": "Prompt_Wranglers_J_5.png",
          "label": "D",
          "softmax_prob": 0.00022543393424712121
        },
        {
          "id": "Prompt_Wranglers_J_5.png",
          "label": "E",
          "softmax_prob": 0.0001357490400550887
        },
        {
          "id": "Prompt_Wranglers_J_5.png",
          "label": "F",
          "softmax_prob": 0.0002673183334991336
        },
        {
          "id": "Prompt_Wranglers_J_5.png",
          "label": "G",
          "softmax_prob": 0.00018644695228431374
        },
        {
          "id": "Prompt_Wranglers_J_5.png",
          "label": "H",
          "softmax_prob": 0.00022617277863901109
        },
        {
          "id": "Prompt_Wranglers_J_5.png",
          "label": "I",
          "softmax_prob": 0.01065878290683031
        },
        {
          "id": "Prompt_Wranglers_J_5.png",
          "label": "J",
          "softmax_prob": 0.000786866876296699
        },
        {
          "id": "Prompt_Wranglers_J_5.png",
          "label": "K",
          "softmax_prob": 0.0003385911986697465
        },
        {
          "id": "Prompt_Wranglers_J_5.png",
          "label": "L",
          "softmax_prob": 0.9842517971992493
        },
        {
          "id": "Prompt_Wranglers_J_5.png",
          "label": "M",
          "softmax_prob": 0.0001382360642310232
        },
        {
          "id": "Prompt_Wranglers_J_5.png",
          "label": "N",
          "softmax_prob": 0.00010879970068344846
        },
        {
          "id": "Prompt_Wranglers_J_5.png",
          "label": "O",
          "softmax_prob": 6.442703306674957e-05
        },
        {
          "id": "Prompt_Wranglers_J_5.png",
          "label": "P",
          "softmax_prob": 0.0003237742930650711
        },
        {
          "id": "Prompt_Wranglers_J_5.png",
          "label": "Q",
          "softmax_prob": 0.00017932547780219465
        },
        {
          "id": "Prompt_Wranglers_J_5.png",
          "label": "R",
          "softmax_prob": 0.0001478852063883096
        },
        {
          "id": "Prompt_Wranglers_J_5.png",
          "label": "S",
          "softmax_prob": 0.00020262475300114602
        },
        {
          "id": "Prompt_Wranglers_J_5.png",
          "label": "T",
          "softmax_prob": 0.0002480780822224915
        },
        {
          "id": "Prompt_Wranglers_J_5.png",
          "label": "U",
          "softmax_prob": 7.723756425548345e-05
        },
        {
          "id": "Prompt_Wranglers_J_5.png",
          "label": "V",
          "softmax_prob": 0.00020583918376360089
        },
        {
          "id": "Prompt_Wranglers_J_5.png",
          "label": "W",
          "softmax_prob": 0.000135991329443641
        },
        {
          "id": "Prompt_Wranglers_J_5.png",
          "label": "X",
          "softmax_prob": 0.00021801432012580335
        },
        {
          "id": "Prompt_Wranglers_J_5.png",
          "label": "Y",
          "softmax_prob": 0.0002658833109308034
        },
        {
          "id": "Prompt_Wranglers_J_5.png",
          "label": "Z",
          "softmax_prob": 0.00022692377388011664
        }
      ]
    },
    {
      "id": "Prompt_Wranglers_J_6.png",
      "raws": [
        {
          "id": "Prompt_Wranglers_J_6.png",
          "label": "A",
          "softmax_prob": 0.022239504382014275
        },
        {
          "id": "Prompt_Wranglers_J_6.png",
          "label": "B",
          "softmax_prob": 0.010886243544518948
        },
        {
          "id": "Prompt_Wranglers_J_6.png",
          "label": "C",
          "softmax_prob": 0.10139258950948715
        },
        {
          "id": "Prompt_Wranglers_J_6.png",
          "label": "D",
          "softmax_prob": 0.05205165222287178
        },
        {
          "id": "Prompt_Wranglers_J_6.png",
          "label": "E",
          "softmax_prob": 0.03635403886437416
        },
        {
          "id": "Prompt_Wranglers_J_6.png",
          "label": "F",
          "softmax_prob": 0.03496025130152702
        },
        {
          "id": "Prompt_Wranglers_J_6.png",
          "label": "G",
          "softmax_prob": 0.01712014339864254
        },
        {
          "id": "Prompt_Wranglers_J_6.png",
          "label": "H",
          "softmax_prob": 0.013486267067492008
        },
        {
          "id": "Prompt_Wranglers_J_6.png",
          "label": "I",
          "softmax_prob": 0.26722195744514465
        },
        {
          "id": "Prompt_Wranglers_J_6.png",
          "label": "J",
          "softmax_prob": 0.03862813860177994
        },
        {
          "id": "Prompt_Wranglers_J_6.png",
          "label": "K",
          "softmax_prob": 0.018760543316602707
        },
        {
          "id": "Prompt_Wranglers_J_6.png",
          "label": "L",
          "softmax_prob": 0.02918204478919506
        },
        {
          "id": "Prompt_Wranglers_J_6.png",
          "label": "M",
          "softmax_prob": 0.016946371644735336
        },
        {
          "id": "Prompt_Wranglers_J_6.png",
          "label": "N",
          "softmax_prob": 0.009082379750907421
        },
        {
          "id": "Prompt_Wranglers_J_6.png",
          "label": "O",
          "softmax_prob": 0.06769989430904388
        },
        {
          "id": "Prompt_Wranglers_J_6.png",
          "label": "P",
          "softmax_prob": 0.009531109593808651
        },
        {
          "id": "Prompt_Wranglers_J_6.png",
          "label": "Q",
          "softmax_prob": 0.012831859290599823
        },
        {
          "id": "Prompt_Wranglers_J_6.png",
          "label": "R",
          "softmax_prob": 0.010427284054458141
        },
        {
          "id": "Prompt_Wranglers_J_6.png",
          "label": "S",
          "softmax_prob": 0.03549426048994064
        },
        {
          "id": "Prompt_Wranglers_J_6.png",
          "label": "T",
          "softmax_prob": 0.0427454337477684
        },
        {
          "id": "Prompt_Wranglers_J_6.png",
          "label": "U",
          "softmax_prob": 0.02296574041247368
        },
        {
          "id": "Prompt_Wranglers_J_6.png",
          "label": "V",
          "softmax_prob": 0.017312778159976006
        },
        {
          "id": "Prompt_Wranglers_J_6.png",
          "label": "W",
          "softmax_prob": 0.01395703386515379
        },
        {
          "id": "Prompt_Wranglers_J_6.png",
          "label": "X",
          "softmax_prob": 0.01711888052523136
        },
        {
          "id": "Prompt_Wranglers_J_6.png",
          "label": "Y",
          "softmax_prob": 0.01906980574131012
        },
        {
          "id": "Prompt_Wranglers_J_6.png",
          "label": "Z",
          "softmax_prob": 0.0625336691737175
        }
      ]
    },
    {
      "id": "Prompt_Wranglers_J_8.png",
      "raws": [
        {
          "id": "Prompt_Wranglers_J_8.png",
          "label": "A",
          "softmax_prob": 0.0005541187128983438
        },
        {
          "id": "Prompt_Wranglers_J_8.png",
          "label": "B",
          "softmax_prob": 0.0008257238660007715
        },
        {
          "id": "Prompt_Wranglers_J_8.png",
          "label": "C",
          "softmax_prob": 0.0005230077658779919
        },
        {
          "id": "Prompt_Wranglers_J_8.png",
          "label": "D",
          "softmax_prob": 0.0012206333922222257
        },
        {
          "id": "Prompt_Wranglers_J_8.png",
          "label": "E",
          "softmax_prob": 0.0011062690755352378
        },
        {
          "id": "Prompt_Wranglers_J_8.png",
          "label": "F",
          "softmax_prob": 0.002611527219414711
        },
        {
          "id": "Prompt_Wranglers_J_8.png",
          "label": "G",
          "softmax_prob": 0.0015437656547874212
        },
        {
          "id": "Prompt_Wranglers_J_8.png",
          "label": "H",
          "softmax_prob": 0.007426424417644739
        },
        {
          "id": "Prompt_Wranglers_J_8.png",
          "label": "I",
          "softmax_prob": 0.0032811604905873537
        },
        {
          "id": "Prompt_Wranglers_J_8.png",
          "label": "J",
          "softmax_prob": 0.8239127397537231
        },
        {
          "id": "Prompt_Wranglers_J_8.png",
          "label": "K",
          "softmax_prob": 0.00104788807220757
        },
        {
          "id": "Prompt_Wranglers_J_8.png",
          "label": "L",
          "softmax_prob": 0.0765022337436676
        },
        {
          "id": "Prompt_Wranglers_J_8.png",
          "label": "M",
          "softmax_prob": 0.001051770756021142
        },
        {
          "id": "Prompt_Wranglers_J_8.png",
          "label": "N",
          "softmax_prob": 0.0017569772899150848
        },
        {
          "id": "Prompt_Wranglers_J_8.png",
          "label": "O",
          "softmax_prob": 0.0002564492169767618
        },
        {
          "id": "Prompt_Wranglers_J_8.png",
          "label": "P",
          "softmax_prob": 0.0013704638695344329
        },
        {
          "id": "Prompt_Wranglers_J_8.png",
          "label": "Q",
          "softmax_prob": 0.0004015722661279142
        },
        {
          "id": "Prompt_Wranglers_J_8.png",
          "label": "R",
          "softmax_prob": 0.0005139205604791641
        },
        {
          "id": "Prompt_Wranglers_J_8.png",
          "label": "S",
          "softmax_prob": 0.001706994604319334
        },
        {
          "id": "Prompt_Wranglers_J_8.png",
          "label": "T",
          "softmax_prob": 0.0013003932544961572
        },
        {
          "id": "Prompt_Wranglers_J_8.png",
          "label": "U",
          "softmax_prob": 0.05773727223277092
        },
        {
          "id": "Prompt_Wranglers_J_8.png",
          "label": "V",
          "softmax_prob": 0.0014818100025877357
        },
        {
          "id": "Prompt_Wranglers_J_8.png",
          "label": "W",
          "softmax_prob": 0.006845361087471247
        },
        {
          "id": "Prompt_Wranglers_J_8.png",
          "label": "X",
          "softmax_prob": 0.0006196837057359517
        },
        {
          "id": "Prompt_Wranglers_J_8.png",
          "label": "Y",
          "softmax_prob": 0.0038176202215254307
        },
        {
          "id": "Prompt_Wranglers_J_8.png",
          "label": "Z",
          "softmax_prob": 0.0005842003738507628
        }
      ]
    },
    {
      "id": "Prompt_Wranglers_J_9.png",
      "raws": [
        {
          "id": "Prompt_Wranglers_J_9.png",
          "label": "A",
          "softmax_prob": 0.00044409133261069655
        },
        {
          "id": "Prompt_Wranglers_J_9.png",
          "label": "B",
          "softmax_prob": 0.0005739514599554241
        },
        {
          "id": "Prompt_Wranglers_J_9.png",
          "label": "C",
          "softmax_prob": 0.00043303988059051335
        },
        {
          "id": "Prompt_Wranglers_J_9.png",
          "label": "D",
          "softmax_prob": 0.000741774623747915
        },
        {
          "id": "Prompt_Wranglers_J_9.png",
          "label": "E",
          "softmax_prob": 0.00046222953824326396
        },
        {
          "id": "Prompt_Wranglers_J_9.png",
          "label": "F",
          "softmax_prob": 0.0013163136318325996
        },
        {
          "id": "Prompt_Wranglers_J_9.png",
          "label": "G",
          "softmax_prob": 0.0011616189731284976
        },
        {
          "id": "Prompt_Wranglers_J_9.png",
          "label": "H",
          "softmax_prob": 0.0008861727546900511
        },
        {
          "id": "Prompt_Wranglers_J_9.png",
          "label": "I",
          "softmax_prob": 0.006510911509394646
        },
        {
          "id": "Prompt_Wranglers_J_9.png",
          "label": "J",
          "softmax_prob": 0.8139249086380005
        },
        {
          "id": "Prompt_Wranglers_J_9.png",
          "label": "K",
          "softmax_prob": 0.0006515619461424649
        },
        {
          "id": "Prompt_Wranglers_J_9.png",
          "label": "L",
          "softmax_prob": 0.1609725058078766
        },
        {
          "id": "Prompt_Wranglers_J_9.png",
          "label": "M",
          "softmax_prob": 0.000380667916033417
        },
        {
          "id": "Prompt_Wranglers_J_9.png",
          "label": "N",
          "softmax_prob": 0.000441392621723935
        },
        {
          "id": "Prompt_Wranglers_J_9.png",
          "label": "O",
          "softmax_prob": 0.0003337739035487175
        },
        {
          "id": "Prompt_Wranglers_J_9.png",
          "label": "P",
          "softmax_prob": 0.0014003135729581118
        },
        {
          "id": "Prompt_Wranglers_J_9.png",
          "label": "Q",
          "softmax_prob": 0.00035621976712718606
        },
        {
          "id": "Prompt_Wranglers_J_9.png",
          "label": "R",
          "softmax_prob": 0.0004238807887304574
        },
        {
          "id": "Prompt_Wranglers_J_9.png",
          "label": "S",
          "softmax_prob": 0.003674483625218272
        },
        {
          "id": "Prompt_Wranglers_J_9.png",
          "label": "T",
          "softmax_prob": 0.0009506684145890176
        },
        {
          "id": "Prompt_Wranglers_J_9.png",
          "label": "U",
          "softmax_prob": 0.0006134160794317722
        },
        {
          "id": "Prompt_Wranglers_J_9.png",
          "label": "V",
          "softmax_prob": 0.0006675796466879547
        },
        {
          "id": "Prompt_Wranglers_J_9.png",
          "label": "W",
          "softmax_prob": 0.00038139140815474093
        },
        {
          "id": "Prompt_Wranglers_J_9.png",
          "label": "X",
          "softmax_prob": 0.0005157465348020196
        },
        {
          "id": "Prompt_Wranglers_J_9.png",
          "label": "Y",
          "softmax_prob": 0.0009757978259585798
        },
        {
          "id": "Prompt_Wranglers_J_9.png",
          "label": "Z",
          "softmax_prob": 0.0008056557271629572
        }
      ]
    }
  ]
}