{
  "count": 9,
  "similarityRate": 0.0034589011613408932,
  "trials": [
    {
      "id": "E_N_1.png",
      "label": "N",
      "similarity": 0.00344446231611073
    },
    {
      "id": "E_N_10.png",
      "label": "N",
      "similarity": 0.002147324848920107
    },
    {
      "id": "E_N_3.png",
      "label": "N",
      "similarity": 0.0001245460589416325
    },
    {
      "id": "E_N_4.png",
      "label": "N",
      "similarity": 0.0002672470873221755
    },
    {
      "id": "E_N_5.png",
      "label": "N",
      "similarity": 0.0003166551177855581
    },
    {
      "id": "E_N_6.png",
      "label": "N",
      "similarity": 0.0003992287383880466
    },
    {
      "id": "E_N_7.png",
      "label": "N",
      "similarity": 0.00013279933773446828
    },
    {
      "id": "E_N_8.png",
      "label": "N",
      "similarity": 0.0033833147026598454
    },
    {
      "id": "E_N_9.png",
      "label": "N",
      "similarity": 0.020914532244205475
    }
  ],
  "similarities": [
    {
      "id": "E_N_1.png",
      "raws": [
        {
          "id": "E_N_1.png",
          "label": "A",
          "softmax_prob": 0.011875947937369347
        },
        {
          "id": "E_N_1.png",
          "label": "B",
          "softmax_prob": 0.0017715495778247714
        },
        {
          "id": "E_N_1.png",
          "label": "C",
          "softmax_prob": 0.10064485669136047
        },
        {
          "id": "E_N_1.png",
          "label": "D",
          "softmax_prob": 0.0043260627426207066
        },
        {
          "id": "E_N_1.png",
          "label": "E",
          "softmax_prob": 0.04189915210008621
        },
        {
          "id": "E_N_1.png",
          "label": "F",
          "softmax_prob": 0.0020189934875816107
        },
        {
          "id": "E_N_1.png",
          "label": "G",
          "softmax_prob": 0.06942319869995117
        },
        {
          "id": "E_N_1.png",
          "label": "H",
          "softmax_prob": 0.018611812964081764
        },
        {
          "id": "E_N_1.png",
          "label": "I",
          "softmax_prob": 0.027127705514431
        },
        {
          "id": "E_N_1.png",
          "label": "J",
          "softmax_prob": 0.019275309517979622
        },
        {
          "id": "E_N_1.png",
          "label": "K",
          "softmax_prob": 0.024983439594507217
        },
        {
          "id": "E_N_1.png",
          "label": "L",
          "softmax_prob": 0.5748416185379028
        },
        {
          "id": "E_N_1.png",
          "label": "M",
          "softmax_prob": 0.017919544130563736
        },
        {
          "id": "E_N_1.png",
          "label": "N",
          "softmax_prob": 0.00344446231611073
        },
        {
          "id": "E_N_1.png",
          "label": "O",
          "softmax_prob": 0.002101196674630046
        },
        {
          "id": "E_N_1.png",
          "label": "P",
          "softmax_prob": 0.003599850693717599
        },
        {
          "id": "E_N_1.png",
          "label": "Q",
          "softmax_prob": 0.0024612823035568
        },
        {
          "id": "E_N_1.png",
          "label": "R",
          "softmax_prob": 0.00643756752833724
        },
        {
          "id": "E_N_1.png",
          "label": "S",
          "softmax_prob": 0.009770261123776436
        },
        {
          "id": "E_N_1.png",
          "label": "T",
          "softmax_prob": 0.0017617978155612946
        },
        {
          "id": "E_N_1.png",
          "label": "U",
          "softmax_prob": 0.024826502427458763
        },
        {
          "id": "E_N_1.png",
          "label": "V",
          "softmax_prob": 0.002445570658892393
        },
        {
          "id": "E_N_1.png",
          "label": "W",
          "softmax_prob": 0.0074472082778811455
        },
        {
          "id": "E_N_1.png",
          "label": "X",
          "softmax_prob": 0.004064349457621574
        },
        {
          "id": "E_N_1.png",
          "label": "Y",
          "softmax_prob": 0.003436838276684284
        },
        {
          "id": "E_N_1.png",
          "label": "Z",
          "softmax_prob": 0.013483881950378418
        }
      ]
    },
    {
      "id": "E_N_10.png",
      "raws": [
        {
          "id": "E_N_10.png",
          "label": "A",
          "softmax_prob": 0.0020784966181963682
        },
        {
          "id": "E_N_10.png",
          "label": "B",
          "softmax_prob": 0.0023920016828924417
        },
        {
          "id": "E_N_10.png",
          "label": "C",
          "softmax_prob": 0.002307099523022771
        },
        {
          "id": "E_N_10.png",
          "label": "D",
          "softmax_prob": 0.005308553576469421
        },
        {
          "id": "E_N_10.png",
          "label": "E",
          "softmax_prob": 0.0036295109894126654
        },
        {
          "id": "E_N_10.png",
          "label": "F",
          "softmax_prob": 0.0072100781835615635
        },
        {
          "id": "E_N_10.png",
          "label": "G",
          "softmax_prob": 0.009362498298287392
        },
        {
          "id": "E_N_10.png",
          "label": "H",
          "softmax_prob": 0.30299967527389526
        },
        {
          "id": "E_N_10.png",
          "label": "I",
          "softmax_prob": 0.06113911047577858
        },
        {
          "id": "E_N_10.png",
          "label": "J",
          "softmax_prob": 0.025455491617321968
        },
        {
          "id": "E_N_10.png",
          "label": "K",
          "softmax_prob": 0.005707594566047192
        },
        {
          "id": "E_N_10.png",
          "label": "L",
          "softmax_prob": 0.511313796043396
        },
        {
          "id": "E_N_10.png",
          "label": "M",
          "softmax_prob": 0.006198463495820761
        },
        {
          "id": "E_N_10.png",
          "label": "N",
          "softmax_prob": 0.002147324848920107
        },
        {
          "id": "E_N_10.png",
          "label": "O",
          "softmax_prob": 0.0021153779234737158
        },
        {
          "id": "E_N_10.png",
          "label": "P",
          "softmax_prob": 0.013807447627186775
        },
        {
          "id": "E_N_10.png",
          "label": "Q",
          "softmax_prob": 0.002421069424599409
        },
        {
          "id": "E_N_10.png",
          "label": "R",
          "softmax_prob": 0.0012452487135306
        },
        {
          "id": "E_N_10.png",
          "label": "S",
          "softmax_prob": 0.005276673939079046
        },
        {
          "id": "E_N_10.png",
          "label": "T",
          "softmax_prob": 0.002356335986405611
        },
        {
          "id": "E_N_10.png",
          "label": "U",
          "softmax_prob": 0.0035250296350568533
        },
        {
          "id": "E_N_10.png",
          "label": "V",
          "softmax_prob": 0.0011895630741491914
        },
        {
          "id": "E_N_10.png",
          "label": "W",
          "softmax_prob": 0.007079114206135273
        },
        {
          "id": "E_N_10.png",
          "label": "X",
          "softmax_prob": 0.002152844564989209
        },
        {
          "id": "E_N_10.png",
          "label": "Y",
          "softmax_prob": 0.0065821497701108456
        },
        {
          "id": "E_N_10.png",
          "label": "Z",
          "softmax_prob": 0.004999459721148014
        }
      ]
    },
    {
      "id": "E_N_3.png",
      "raws": [
        {
          "id": "E_N_3.png",
          "label": "A",
          "softmax_prob": 0.00013964787649456412
        },
        {
          "id": "E_N_3.png",
          "label": "B",
          "softmax_prob": 0.0002460036484990269
        },
        {
          "id": "E_N_3.png",
          "label": "C",
          "softmax_prob": 0.00017707879305817187
        },
        {
          "id": "E_N_3.png",
          "label": "D",
          "softmax_prob": 0.0004996961215510964
        },
        {
          "id": "E_N_3.png",
          "label": "E",
          "softmax_prob": 0.0002153206878574565
        },
        {
          "id": "E_N_3.png",
          "label": "F",
          "softmax_prob": 0.00045792682794854045
        },
        {
          "id": "E_N_3.png",
          "label": "G",
          "softmax_prob": 0.0006046289345249534
        },
        {
          "id": "E_N_3.png",
          "label": "H",
          "softmax_prob": 0.0006364291184581816
        },
        {
          "id": "E_N_3.png",
          "label": "I",
          "softmax_prob": 0.002264929236844182
        },
        {
          "id": "E_N_3.png",
          "label": "J",
          "softmax_prob": 0.005325521808117628
        },
        {
          "id": "E_N_3.png",
          "label": "K",
          "softmax_prob": 0.0005893131601624191
        },
        {
          "id": "E_N_3.png",
          "label": "L",
          "softmax_prob": 0.9844149351119995
        },
        {
          "id": "E_N_3.png",
          "label": "M",
          "softmax_prob": 0.0001608663733350113
        },
        {
          "id": "E_N_3.png",
          "label": "N",
          "softmax_prob": 0.0001245460589416325
        },
        {
          "id": "E_N_3.png",
          "label": "O",
          "softmax_prob": 0.00011173609527759254
        },
        {
          "id": "E_N_3.png",
          "label": "P",
          "softmax_prob": 0.001133417128585279
        },
        {
          "id": "E_N_3.png",
          "label": "Q",
          "softmax_prob": 0.00020706516806967556
        },
        {
          "id": "E_N_3.png",
          "label": "R",
          "softmax_prob": 0.00012765578867401928
        },
        {
          "id": "E_N_3.png",
          "label": "S",
          "softmax_prob": 0.00040757725946605206
        },
        {
          "id": "E_N_3.png",
          "label": "T",
          "softmax_prob": 0.00026121377595700324
        },
        {
          "id": "E_N_3.png",
          "label": "U",
          "softmax_prob": 0.00014049626770429313
        },
        {
          "id": "E_N_3.png",
          "label": "V",
          "softmax_prob": 0.00020098403911106288
        },
        {
          "id": "E_N_3.png",
          "label": "W",
          "softmax_prob": 0.00019932490249630064
        },
        {
          "id": "E_N_3.png",
          "label": "X",
          "softmax_prob": 0.0003033463435713202
        },
        {
          "id": "E_N_3.png",
          "label": "Y",
          "softmax_prob": 0.0007232503849081695
        },
        {
          "id": "E_N_3.png",
          "label": "Z",
          "softmax_prob": 0.00032704108161851764
        }
      ]
    },
    {
      "id": "E_N_4.png",
      "raws": [
        {
          "id": "E_N_4.png",
          "label": "A",
          "softmax_prob": 0.0003125797084067017
        },
        {
          "id": "E_N_4.png",
          "label": "B",
          "softmax_prob": 0.0002955913951154798
        },
        {
          "id": "E_N_4.png",
          "label": "C",
          "softmax_prob": 0.0003966432705055922
        },
        {
          "id": "E_N_4.png",
          "label": "D",
          "softmax_prob": 0.0005745891248807311
        },
        {
          "id": "E_N_4.png",
          "label": "E",
          "softmax_prob": 0.00037297751987352967
        },
        {
          "id": "E_N_4.png",
          "label": "F",
          "softmax_prob": 0.0007569153094664216
        },
        {
          "id": "E_N_4.png",
          "label": "G",
          "softmax_prob": 0.0013884404907003045
        },
        {
          "id": "E_N_4.png",
          "label": "H",
          "softmax_prob": 0.003215018892660737
        },
        {
          "id": "E_N_4.png",
          "label": "I",
          "softmax_prob": 0.012476103380322456
        },
        {
          "id": "E_N_4.png",
          "label": "J",
          "softmax_prob": 0.005356106907129288
        },
        {
          "id": "E_N_4.png",
          "label": "K",
          "softmax_prob": 0.0009757070220075548
        },
        {
          "id": "E_N_4.png",
          "label": "L",
          "softmax_prob": 0.9632317423820496
        },
        {
          "id": "E_N_4.png",
          "label": "M",
          "softmax_prob": 0.0006764866993762553
        },
        {
          "id": "E_N_4.png",
          "label": "N",
          "softmax_prob": 0.0002672470873221755
        },
        {
          "id": "E_N_4.png",
          "label": "O",
          "softmax_prob": 0.00014796019240748137
        },
        {
          "id": "E_N_4.png",
          "label": "P",
          "softmax_prob": 0.00046192255103960633
        },
        {
          "id": "E_N_4.png",
          "label": "Q",
          "softmax_prob": 0.00022331545187626034
        },
        {
          "id": "E_N_4.png",
          "label": "R",
          "softmax_prob": 0.00021836423547938466
        },
        {
          "id": "E_N_4.png",
          "label": "S",
          "softmax_prob": 0.00048576921108178794
        },
        {
          "id": "E_N_4.png",
          "label": "T",
          "softmax_prob": 0.00037475937278941274
        },
        {
          "id": "E_N_4.png",
          "label": "U",
          "softmax_prob": 0.004349071998149157
        },
        {
          "id": "E_N_4.png",
          "label": "V",
          "softmax_prob": 0.000584507011808455
        },
        {
          "id": "E_N_4.png",
          "label": "W",
          "softmax_prob": 0.0011164479656144977
        },
        {
          "id": "E_N_4.png",
          "label": "X",
          "softmax_prob": 0.0005905060097575188
        },
        {
          "id": "E_N_4.png",
          "label": "Y",
          "softmax_prob": 0.0006056667771190405
        },
        {
          "id": "E_N_4.png",
          "label": "Z",
          "softmax_prob": 0.0005455647478811443
        }
      ]
    },
    {
      "id": "E_N_5.png",
      "raws": [
        {
          "id": "E_N_5.png",
          "label": "A",
          "softmax_prob": 0.0005605391343124211
        },
        {
          "id": "E_N_5.png",
          "label": "B",
          "softmax_prob": 0.0014415744226425886
        },
        {
          "id": "E_N_5.png",
          "label": "C",
          "softmax_prob": 0.0009658987401053309
        },
        {
          "id": "E_N_5.png",
          "label": "D",
          "softmax_prob": 0.00035017012851312757
        },
        {
          "id": "E_N_5.png",
          "label": "E",
          "softmax_prob": 0.7215517163276672
        },
        {
          "id": "E_N_5.png",
          "label": "F",
          "softmax_prob": 0.20238560438156128
        },
        {
          "id": "E_N_5.png",
          "label": "G",
          "softmax_prob": 0.0011620701989158988
        },
        {
          "id": "E_N_5.png",
          "label": "H",
          "softmax_prob": 0.0012266658013686538
        },
        {
          "id": "E_N_5.png",
          "label": "I",
          "softmax_prob": 0.03976009786128998
        },
        {
          "id": "E_N_5.png",
          "label": "J",
          "softmax_prob": 0.002994317328557372
        },
        {
          "id": "E_N_5.png",
          "label": "K",
          "softmax_prob": 0.0033340498339384794
        },
        {
          "id": "E_N_5.png",
          "label": "L",
          "softmax_prob": 0.0030570155940949917
        },
        {
          "id": "E_N_5.png",
          "label": "M",
          "softmax_prob": 0.0006635989993810654
        },
        {
          "id": "E_N_5.png",
          "label": "N",
          "softmax_prob": 0.0003166551177855581
        },
        {
          "id": "E_N_5.png",
          "label": "O",
          "softmax_prob": 0.0006459868745878339
        },
        {
          "id": "E_N_5.png",
          "label": "P",
          "softmax_prob": 0.0016911545535549521
        },
        {
          "id": "E_N_5.png",
          "label": "Q",
          "softmax_prob": 0.000764065480325371
        },
        {
          "id": "E_N_5.png",
          "label": "R",
          "softmax_prob": 0.000647370470687747
        },
        {
          "id": "E_N_5.png",
          "label": "S",
          "softmax_prob": 0.0017307531088590622
        },
        {
          "id": "E_N_5.png",
          "label": "T",
          "softmax_prob": 0.000642313330899924
        },
        {
          "id": "E_N_5.png",
          "label": "U",
          "softmax_prob": 0.0009167626849375665
        },
        {
          "id": "E_N_5.png",
          "label": "V",
          "softmax_prob": 0.0014144463930279016
        },
        {
          "id": "E_N_5.png",
          "label": "W",
          "softmax_prob": 0.0007775534759275615
        },
        {
          "id": "E_N_5.png",
          "label": "X",
          "softmax_prob": 0.0015917150303721428
        },
        {
          "id": "E_N_5.png",
          "label": "Y",
          "softmax_prob": 0.0021373089402914047
        },
        {
          "id": "E_N_5.png",
          "label": "Z",
          "softmax_prob": 0.007270555477589369
        }
      ]
    },
    {
      "id": "E_N_6.png",
      "raws": [
        {
          "id": "E_N_6.png",
          "label": "A",
          "softmax_prob": 0.0003361520648468286
        },
        {
          "id": "E_N_6.png",
          "label": "B",
          "softmax_prob": 0.00020745220535900444
        },
        {
          "id": "E_N_6.png",
          "label": "C",
          "softmax_prob": 0.0017472859472036362
        },
        {
          "id": "E_N_6.png",
          "label": "D",
          "softmax_prob": 0.00022694820654578507
        },
        {
          "id": "E_N_6.png",
          "label": "E",
          "softmax_prob": 0.001700892229564488
        },
        {
          "id": "E_N_6.png",
          "label": "F",
          "softmax_prob": 0.0006269169971346855
        },
        {
          "id": "E_N_6.png",
          "label": "G",
          "softmax_prob": 0.002436661859974265
        },
        {
          "id": "E_N_6.png",
          "label": "H",
          "softmax_prob": 0.00084191799396649
        },
        {
          "id": "E_N_6.png",
          "label": "I",
          "softmax_prob": 0.005307204555720091
        },
        {
          "id": "E_N_6.png",
          "label": "J",
          "softmax_prob": 0.0014881612733006477
        },
        {
          "id": "E_N_6.png",
          "label": "K",
          "softmax_prob": 0.0017957516247406602
        },
        {
          "id": "E_N_6.png",
          "label": "L",
          "softmax_prob": 0.9748753905296326
        },
        {
          "id": "E_N_6.png",
          "label": "M",
          "softmax_prob": 0.0007347629871219397
        },
        {
          "id": "E_N_6.png",
          "label": "N",
          "softmax_prob": 0.0003992287383880466
        },
        {
          "id": "E_N_6.png",
          "label": "O",
          "softmax_prob": 0.00021637362078763545
        },
        {
          "id": "E_N_6.png",
          "label": "P",
          "softmax_prob": 0.0003560501500032842
        },
        {
          "id": "E_N_6.png",
          "label": "Q",
          "softmax_prob": 0.00038910869625397027
        },
        {
          "id": "E_N_6.png",
          "label": "R",
          "softmax_prob": 0.0008235907298512757
        },
        {
          "id": "E_N_6.png",
          "label": "S",
          "softmax_prob": 0.0010343657340854406
        },
        {
          "id": "E_N_6.png",
          "label": "T",
          "softmax_prob": 0.00048287262325175107
        },
        {
          "id": "E_N_6.png",
          "label": "U",
          "softmax_prob": 0.0008384401444345713
        },
        {
          "id": "E_N_6.png",
          "label": "V",
          "softmax_prob": 0.00028620625380426645
        },
        {
          "id": "E_N_6.png",
          "label": "W",
          "softmax_prob": 0.00034190938458777964
        },
        {
          "id": "E_N_6.png",
          "label": "X",
          "softmax_prob": 0.0005432675243355334
        },
        {
          "id": "E_N_6.png",
          "label": "Y",
          "softmax_prob": 0.00048431780305691063
        },
        {
          "id": "E_N_6.png",
          "label": "Z",
          "softmax_prob": 0.0014786107931286097
        }
      ]
    },
    {
      "id": "E_N_7.png",
      "raws": [
        {
          "id": "E_N_7.png",
          "label": "A",
          "softmax_prob": 0.0001564863050589338
        },
        {
          "id": "E_N_7.png",
          "label": "B",
          "softmax_prob": 0.0007429573452100158
        },
        {
          "id": "E_N_7.png",
          "label": "C",
          "softmax_prob": 0.00020912979380227625
        },
        {
          "id": "E_N_7.png",
          "label": "D",
          "softmax_prob": 0.00014095047663431615
        },
        {
          "id": "E_N_7.png",
          "label": "E",
          "softmax_prob": 0.010296921245753765
        },
        {
          "id": "E_N_7.png",
          "label": "F",
          "softmax_prob": 0.9711315631866455
        },
        {
          "id": "E_N_7.png",
          "label": "G",
          "softmax_prob": 0.0002956651442218572
        },
        {
          "id": "E_N_7.png",
          "label": "H",
          "softmax_prob": 0.0004922889056615531
        },
        {
          "id": "E_N_7.png",
          "label": "I",
          "softmax_prob": 0.006362449377775192
        },
        {
          "id": "E_N_7.png",
          "label": "J",
          "softmax_prob": 0.0019578509964048862
        },
        {
          "id": "E_N_7.png",
          "label": "K",
          "softmax_prob": 0.0008940797415561974
        },
        {
          "id": "E_N_7.png",
          "label": "L",
          "softmax_prob": 0.0008874943014234304
        },
        {
          "id": "E_N_7.png",
          "label": "M",
          "softmax_prob": 0.00016425622743554413
        },
        {
          "id": "E_N_7.png",
          "label": "N",
          "softmax_prob": 0.00013279933773446828
        },
        {
          "id": "E_N_7.png",
          "label": "O",
          "softmax_prob": 0.00027457522810436785
        },
        {
          "id": "E_N_7.png",
          "label": "P",
          "softmax_prob": 0.0007659271941520274
        },
        {
          "id": "E_N_7.png",
          "label": "Q",
          "softmax_prob": 0.00023546711599919945
        },
        {
          "id": "E_N_7.png",
          "label": "R",
          "softmax_prob": 0.0002195806009694934
        },
        {
          "id": "E_N_7.png",
          "label": "S",
          "softmax_prob": 0.0006858871201984584
        },
        {
          "id": "E_N_7.png",
          "label": "T",
          "softmax_prob": 0.0001917789486469701
        },
        {
          "id": "E_N_7.png",
          "label": "U",
          "softmax_prob": 0.0002694204158615321
        },
        {
          "id": "E_N_7.png",
          "label": "V",
          "softmax_prob": 0.0006515822024084628
        },
        {
          "id": "E_N_7.png",
          "label": "W",
          "softmax_prob": 0.0003033968387171626
        },
        {
          "id": "E_N_7.png",
          "label": "X",
          "softmax_prob": 0.0003744868445210159
        },
        {
          "id": "E_N_7.png",
          "label": "Y",
          "softmax_prob": 0.0008106055902317166
        },
        {
          "id": "E_N_7.png",
          "label": "Z",
          "softmax_prob": 0.001352594350464642
        }
      ]
    },
    {
      "id": "E_N_8.png",
      "raws": [
        {
          "id": "E_N_8.png",
          "label": "A",
          "softmax_prob": 0.0100210877135396
        },
        {
          "id": "E_N_8.png",
          "label": "B",
          "softmax_prob": 0.012560426257550716
        },
        {
          "id": "E_N_8.png",
          "label": "C",
          "softmax_prob": 0.008366462774574757
        },
        {
          "id": "E_N_8.png",
          "label": "D",
          "softmax_prob": 0.04239838942885399
        },
        {
          "id": "E_N_8.png",
          "label": "E",
          "softmax_prob": 0.010747969150543213
        },
        {
          "id": "E_N_8.png",
          "label": "F",
          "softmax_prob": 0.01306112203747034
        },
        {
          "id": "E_N_8.png",
          "label": "G",
          "softmax_prob": 0.030993489548563957
        },
        {
          "id": "E_N_8.png",
          "label": "H",
          "softmax_prob": 0.026754742488265038
        },
        {
          "id": "E_N_8.png",
          "label": "I",
          "softmax_prob": 0.23688893020153046
        },
        {
          "id": "E_N_8.png",
          "label": "J",
          "softmax_prob": 0.09643511474132538
        },
        {
          "id": "E_N_8.png",
          "label": "K",
          "softmax_prob": 0.00833603460341692
        },
        {
          "id": "E_N_8.png",
          "label": "L",
          "softmax_prob": 0.3169559836387634
        },
        {
          "id": "E_N_8.png",
          "label": "M",
          "softmax_prob": 0.006298820488154888
        },
        {
          "id": "E_N_8.png",
          "label": "N",
          "softmax_prob": 0.0033833147026598454
        },
        {
          "id": "E_N_8.png",
          "label": "O",
          "softmax_prob": 0.0160316601395607
        },
        {
          "id": "E_N_8.png",
          "label": "P",
          "softmax_prob": 0.0054881698451936245
        },
        {
          "id": "E_N_8.png",
          "label": "Q",
          "softmax_prob": 0.0054076481610536575
        },
        {
          "id": "E_N_8.png",
          "label": "R",
          "softmax_prob": 0.003468044800683856
        },
        {
          "id": "E_N_8.png",
          "label": "S",
          "softmax_prob": 0.01900191232562065
        },
        {
          "id": "E_N_8.png",
          "label": "T",
          "softmax_prob": 0.007461343426257372
        },
        {
          "id": "E_N_8.png",
          "label": "U",
          "softmax_prob": 0.04585786908864975
        },
        {
          "id": "E_N_8.png",
          "label": "V",
          "softmax_prob": 0.008497103117406368
        },
        {
          "id": "E_N_8.png",
          "label": "W",
          "softmax_prob": 0.013949614949524403
        },
        {
          "id": "E_N_8.png",
          "label": "X",
          "softmax_prob": 0.00747915543615818
        },
        {
          "id": "E_N_8.png",
          "label": "Y",
          "softmax_prob": 0.01642165333032608
        },
        {
          "id": "E_N_8.png",
          "label": "Z",
          "softmax_prob": 0.02773395925760269
        }
      ]
    },
    {
      "id": "E_N_9.png",
      "raws": [
        {
          "id": "E_N_9.png",
          "label": "A",
          "softmax_prob": 0.04187719523906708
        },
        {
          "id": "E_N_9.png",
          "label": "B",
          "softmax_prob": 0.01786961406469345
        },
        {
          "id": "E_N_9.png",
          "label": "C",
          "softmax_prob": 0.045913804322481155
        },
        {
          "id": "E_N_9.png",
          "label": "D",
          "softmax_prob": 0.0479656420648098
        },
        {
          "id": "E_N_9.png",
          "label": "E",
          "softmax_prob": 0.04148290306329727
        },
        {
          "id": "E_N_9.png",
          "label": "F",
          "softmax_prob": 0.025513039901852608
        },
        {
          "id": "E_N_9.png",
          "label": "G",
          "softmax_prob": 0.04943319410085678
        },
        {
          "id": "E_N_9.png",
          "label": "H",
          "softmax_prob": 0.022692346945405006
        },
        {
          "id": "E_N_9.png",
          "label": "I",
          "softmax_prob": 0.07288907468318939
        },
        {
          "id": "E_N_9.png",
          "label": "J",
          "softmax_prob": 0.0742977187037468
        },
        {
          "id": "E_N_9.png",
          "label": "K",
          "softmax_prob": 0.020630810409784317
        },
        {
          "id": "E_N_9.png",
          "label": "L",
          "softmax_prob": 0.029514959082007408
        },
        {
          "id": "E_N_9.png",
          "label": "M",
          "softmax_prob": 0.018718816339969635
        },
        {
          "id": "E_N_9.png",
          "label": "N",
          "softmax_prob": 0.020914532244205475
        },
        {
          "id": "E_N_9.png",
          "label": "O",
          "softmax_prob": 0.051793474704027176
        },
        {
          "id": "E_N_9.png",
          "label": "P",
          "softmax_prob": 0.015974778681993484
        },
        {
          "id": "E_N_9.png",
          "label": "Q",
          "softmax_prob": 0.03001086786389351
        },
        {
          "id": "E_N_9.png",
          "label": "R",
          "softmax_prob": 0.03174848109483719
        },
        {
          "id": "E_N_9.png",
          "label": "S",
          "softmax_prob": 0.030325697734951973
        },
        {
          "id": "E_N_9.png",
          "label": "T",
          "softmax_prob": 0.07258273661136627
        },
        {
          "id": "E_N_9.png",
          "label": "U",
          "softmax_prob": 0.04212253913283348
        },
        {
          "id": "E_N_9.png",
          "label": "V",
          "softmax_prob": 0.04280981421470642
        },
        {
          "id": "E_N_9.png",
          "label": "W",
          "softmax_prob": 0.027465054765343666
        },
        {
          "id": "E_N_9.png",
          "label": "X",
          "softmax_prob": 0.03776329755783081
        },
        {
          "id": "E_N_9.png",
          "label": "Y",
          "softmax_prob": 0.04351383075118065
        },
        {
          "id": "E_N_9.png",
          "label": "Z",
          "softmax_prob": 0.04417581483721733
        }
      ]
    }
  ]
}