{
  "count": 10,
  "similarityRate": 0.006121762912516715,
  "trials": [
    {
      "id": "K_B_1.png",
      "label": "B",
      "similarity": 0.003625374287366867
    },
    {
      "id": "K_B_10.png",
      "label": "B",
      "similarity": 0.000678537820931524
    },
    {
      "id": "K_B_2.png",
      "label": "B",
      "similarity": 0.015463470481336117
    },
    {
      "id": "K_B_3.png",
      "label": "B",
      "similarity": 0.010765899904072285
    },
    {
      "id": "K_B_4.png",
      "label": "B",
      "similarity": 0.004271652549505234
    },
    {
      "id": "K_B_5.png",
      "label": "B",
      "similarity": 0.010886243544518948
    },
    {
      "id": "K_B_6.png",
      "label": "B",
      "similarity": 0.002362698782235384
    },
    {
      "id": "K_B_7.png",
      "label": "B",
      "similarity": 5.572697409661487e-05
    },
    {
      "id": "K_B_8.png",
      "label": "B",
      "similarity": 0.000609122624155134
    },
    {
      "id": "K_B_9.png",
      "label": "B",
      "similarity": 0.012498902156949043
    }
  ],
  "similarities": [
    {
      "id": "K_B_1.png",
      "raws": [
        {
          "id": "K_B_1.png",
          "label": "A",
          "softmax_prob": 0.009641621261835098
        },
        {
          "id": "K_B_1.png",
          "label": "B",
          "softmax_prob": 0.003625374287366867
        },
        {
          "id": "K_B_1.png",
          "label": "C",
          "softmax_prob": 0.014816904440522194
        },
        {
          "id": "K_B_1.png",
          "label": "D",
          "softmax_prob": 0.013443302363157272
        },
        {
          "id": "K_B_1.png",
          "label": "E",
          "softmax_prob": 0.016449695453047752
        },
        {
          "id": "K_B_1.png",
          "label": "F",
          "softmax_prob": 0.2694332003593445
        },
        {
          "id": "K_B_1.png",
          "label": "G",
          "softmax_prob": 0.006322749890387058
        },
        {
          "id": "K_B_1.png",
          "label": "H",
          "softmax_prob": 0.025538619607686996
        },
        {
          "id": "K_B_1.png",
          "label": "I",
          "softmax_prob": 0.09292203933000565
        },
        {
          "id": "K_B_1.png",
          "label": "J",
          "softmax_prob": 0.2916734218597412
        },
        {
          "id": "K_B_1.png",
          "label": "K",
          "softmax_prob": 0.011224777437746525
        },
        {
          "id": "K_B_1.png",
          "label": "L",
          "softmax_prob": 0.01661190390586853
        },
        {
          "id": "K_B_1.png",
          "label": "M",
          "softmax_prob": 0.024823816493153572
        },
        {
          "id": "K_B_1.png",
          "label": "N",
          "softmax_prob": 0.00421628262847662
        },
        {
          "id": "K_B_1.png",
          "label": "O",
          "softmax_prob": 0.02028767205774784
        },
        {
          "id": "K_B_1.png",
          "label": "P",
          "softmax_prob": 0.048830024898052216
        },
        {
          "id": "K_B_1.png",
          "label": "Q",
          "softmax_prob": 0.012363790534436703
        },
        {
          "id": "K_B_1.png",
          "label": "R",
          "softmax_prob": 0.0029304572381079197
        },
        {
          "id": "K_B_1.png",
          "label": "S",
          "softmax_prob": 0.01848139613866806
        },
        {
          "id": "K_B_1.png",
          "label": "T",
          "softmax_prob": 0.031914446502923965
        },
        {
          "id": "K_B_1.png",
          "label": "U",
          "softmax_prob": 0.005557462573051453
        },
        {
          "id": "K_B_1.png",
          "label": "V",
          "softmax_prob": 0.007717507891356945
        },
        {
          "id": "K_B_1.png",
          "label": "W",
          "softmax_prob": 0.0046674152836203575
        },
        {
          "id": "K_B_1.png",
          "label": "X",
          "softmax_prob": 0.016924668103456497
        },
        {
          "id": "K_B_1.png",
          "label": "Y",
          "softmax_prob": 0.01300391647964716
        },
        {
          "id": "K_B_1.png",
          "label": "Z",
          "softmax_prob": 0.016577526926994324
        }
      ]
    },
    {
      "id": "K_B_10.png",
      "raws": [
        {
          "id": "K_B_10.png",
          "label": "A",
          "softmax_prob": 0.009019561111927032
        },
        {
          "id": "K_B_10.png",
          "label": "B",
          "softmax_prob": 0.000678537820931524
        },
        {
          "id": "K_B_10.png",
          "label": "C",
          "softmax_prob": 0.0014476240612566471
        },
        {
          "id": "K_B_10.png",
          "label": "D",
          "softmax_prob": 0.01177302934229374
        },
        {
          "id": "K_B_10.png",
          "label": "E",
          "softmax_prob": 0.0010308686178177595
        },
        {
          "id": "K_B_10.png",
          "label": "F",
          "softmax_prob": 0.0005068565369583666
        },
        {
          "id": "K_B_10.png",
          "label": "G",
          "softmax_prob": 0.0013520834036171436
        },
        {
          "id": "K_B_10.png",
          "label": "H",
          "softmax_prob": 0.1022467240691185
        },
        {
          "id": "K_B_10.png",
          "label": "I",
          "softmax_prob": 0.0034703933633863926
        },
        {
          "id": "K_B_10.png",
          "label": "J",
          "softmax_prob": 0.0012278686044737697
        },
        {
          "id": "K_B_10.png",
          "label": "K",
          "softmax_prob": 0.0020146772731095552
        },
        {
          "id": "K_B_10.png",
          "label": "L",
          "softmax_prob": 0.003168128663673997
        },
        {
          "id": "K_B_10.png",
          "label": "M",
          "softmax_prob": 0.7675665616989136
        },
        {
          "id": "K_B_10.png",
          "label": "N",
          "softmax_prob": 0.07145237177610397
        },
        {
          "id": "K_B_10.png",
          "label": "O",
          "softmax_prob": 0.0025878159794956446
        },
        {
          "id": "K_B_10.png",
          "label": "P",
          "softmax_prob": 0.0019719148986041546
        },
        {
          "id": "K_B_10.png",
          "label": "Q",
          "softmax_prob": 0.00038816238520666957
        },
        {
          "id": "K_B_10.png",
          "label": "R",
          "softmax_prob": 0.00042308290721848607
        },
        {
          "id": "K_B_10.png",
          "label": "S",
          "softmax_prob": 0.0016831717221066356
        },
        {
          "id": "K_B_10.png",
          "label": "T",
          "softmax_prob": 0.0005527796456590295
        },
        {
          "id": "K_B_10.png",
          "label": "U",
          "softmax_prob": 0.0038704145699739456
        },
        {
          "id": "K_B_10.png",
          "label": "V",
          "softmax_prob": 0.000623851316049695
        },
        {
          "id": "K_B_10.png",
          "label": "W",
          "softmax_prob": 0.0061439876444637775
        },
        {
          "id": "K_B_10.png",
          "label": "X",
          "softmax_prob": 0.0018998341402038932
        },
        {
          "id": "K_B_10.png",
          "label": "Y",
          "softmax_prob": 0.0016356201376765966
        },
        {
          "id": "K_B_10.png",
          "label": "Z",
          "softmax_prob": 0.0012642021756619215
        }
      ]
    },
    {
      "id": "K_B_2.png",
      "raws": [
        {
          "id": "K_B_2.png",
          "label": "A",
          "softmax_prob": 0.0010543819516897202
        },
        {
          "id": "K_B_2.png",
          "label": "B",
          "softmax_prob": 0.015463470481336117
        },
        {
          "id": "K_B_2.png",
          "label": "C",
          "softmax_prob": 0.0020492221228778362
        },
        {
          "id": "K_B_2.png",
          "label": "D",
          "softmax_prob": 0.002818071749061346
        },
        {
          "id": "K_B_2.png",
          "label": "E",
          "softmax_prob": 0.4145221710205078
        },
        {
          "id": "K_B_2.png",
          "label": "F",
          "softmax_prob": 0.3737102150917053
        },
        {
          "id": "K_B_2.png",
          "label": "G",
          "softmax_prob": 0.003597948234528303
        },
        {
          "id": "K_B_2.png",
          "label": "H",
          "softmax_prob": 0.010564900003373623
        },
        {
          "id": "K_B_2.png",
          "label": "I",
          "softmax_prob": 0.016296477988362312
        },
        {
          "id": "K_B_2.png",
          "label": "J",
          "softmax_prob": 0.007682241033762693
        },
        {
          "id": "K_B_2.png",
          "label": "K",
          "softmax_prob": 0.004857431631535292
        },
        {
          "id": "K_B_2.png",
          "label": "L",
          "softmax_prob": 0.005049138329923153
        },
        {
          "id": "K_B_2.png",
          "label": "M",
          "softmax_prob": 0.0015659283380955458
        },
        {
          "id": "K_B_2.png",
          "label": "N",
          "softmax_prob": 0.000647141074296087
        },
        {
          "id": "K_B_2.png",
          "label": "O",
          "softmax_prob": 0.005211720708757639
        },
        {
          "id": "K_B_2.png",
          "label": "P",
          "softmax_prob": 0.006692664232105017
        },
        {
          "id": "K_B_2.png",
          "label": "Q",
          "softmax_prob": 0.002807329874485731
        },
        {
          "id": "K_B_2.png",
          "label": "R",
          "softmax_prob": 0.0031575807370245457
        },
        {
          "id": "K_B_2.png",
          "label": "S",
          "softmax_prob": 0.0053303977474570274
        },
        {
          "id": "K_B_2.png",
          "label": "T",
          "softmax_prob": 0.0013468150282278657
        },
        {
          "id": "K_B_2.png",
          "label": "U",
          "softmax_prob": 0.0042709908448159695
        },
        {
          "id": "K_B_2.png",
          "label": "V",
          "softmax_prob": 0.003928050398826599
        },
        {
          "id": "K_B_2.png",
          "label": "W",
          "softmax_prob": 0.0015684025129303336
        },
        {
          "id": "K_B_2.png",
          "label": "X",
          "softmax_prob": 0.0036104493774473667
        },
        {
          "id": "K_B_2.png",
          "label": "Y",
          "softmax_prob": 0.0026966899167746305
        },
        {
          "id": "K_B_2.png",
          "label": "Z",
          "softmax_prob": 0.0995001420378685
        }
      ]
    },
    {
      "id": "K_B_3.png",
      "raws": [
        {
          "id": "K_B_3.png",
          "label": "A",
          "softmax_prob": 0.001400012755766511
        },
        {
          "id": "K_B_3.png",
          "label": "B",
          "softmax_prob": 0.010765899904072285
        },
        {
          "id": "K_B_3.png",
          "label": "C",
          "softmax_prob": 0.0043872338719666
        },
        {
          "id": "K_B_3.png",
          "label": "D",
          "softmax_prob": 0.0007416531443595886
        },
        {
          "id": "K_B_3.png",
          "label": "E",
          "softmax_prob": 0.10039510577917099
        },
        {
          "id": "K_B_3.png",
          "label": "F",
          "softmax_prob": 0.4724462330341339
        },
        {
          "id": "K_B_3.png",
          "label": "G",
          "softmax_prob": 0.006794041022658348
        },
        {
          "id": "K_B_3.png",
          "label": "H",
          "softmax_prob": 0.10628286004066467
        },
        {
          "id": "K_B_3.png",
          "label": "I",
          "softmax_prob": 0.011959376744925976
        },
        {
          "id": "K_B_3.png",
          "label": "J",
          "softmax_prob": 0.006307575386017561
        },
        {
          "id": "K_B_3.png",
          "label": "K",
          "softmax_prob": 0.15199865400791168
        },
        {
          "id": "K_B_3.png",
          "label": "L",
          "softmax_prob": 0.011101674288511276
        },
        {
          "id": "K_B_3.png",
          "label": "M",
          "softmax_prob": 0.003790277522057295
        },
        {
          "id": "K_B_3.png",
          "label": "N",
          "softmax_prob": 0.001745658810250461
        },
        {
          "id": "K_B_3.png",
          "label": "O",
          "softmax_prob": 0.0026547310408204794
        },
        {
          "id": "K_B_3.png",
          "label": "P",
          "softmax_prob": 0.00642020208761096
        },
        {
          "id": "K_B_3.png",
          "label": "Q",
          "softmax_prob": 0.004950693342834711
        },
        {
          "id": "K_B_3.png",
          "label": "R",
          "softmax_prob": 0.019598156213760376
        },
        {
          "id": "K_B_3.png",
          "label": "S",
          "softmax_prob": 0.009238709695637226
        },
        {
          "id": "K_B_3.png",
          "label": "T",
          "softmax_prob": 0.002635433804243803
        },
        {
          "id": "K_B_3.png",
          "label": "U",
          "softmax_prob": 0.005105683114379644
        },
        {
          "id": "K_B_3.png",
          "label": "V",
          "softmax_prob": 0.0032832773867994547
        },
        {
          "id": "K_B_3.png",
          "label": "W",
          "softmax_prob": 0.005544680170714855
        },
        {
          "id": "K_B_3.png",
          "label": "X",
          "softmax_prob": 0.012684774585068226
        },
        {
          "id": "K_B_3.png",
          "label": "Y",
          "softmax_prob": 0.006822632625699043
        },
        {
          "id": "K_B_3.png",
          "label": "Z",
          "softmax_prob": 0.030944809317588806
        }
      ]
    },
    {
      "id": "K_B_4.png",
      "raws": [
        {
          "id": "K_B_4.png",
          "label": "A",
          "softmax_prob": 0.2421637326478958
        },
        {
          "id": "K_B_4.png",
          "label": "B",
          "softmax_prob": 0.004271652549505234
        },
        {
          "id": "K_B_4.png",
          "label": "C",
          "softmax_prob": 0.10409433394670486
        },
        {
          "id": "K_B_4.png",
          "label": "D",
          "softmax_prob": 0.029141390696167946
        },
        {
          "id": "K_B_4.png",
          "label": "E",
          "softmax_prob": 0.009701025672256947
        },
        {
          "id": "K_B_4.png",
          "label": "F",
          "softmax_prob": 0.0029182799626141787
        },
        {
          "id": "K_B_4.png",
          "label": "G",
          "softmax_prob": 0.003019902855157852
        },
        {
          "id": "K_B_4.png",
          "label": "H",
          "softmax_prob": 0.11959552019834518
        },
        {
          "id": "K_B_4.png",
          "label": "I",
          "softmax_prob": 0.01168903335928917
        },
        {
          "id": "K_B_4.png",
          "label": "J",
          "softmax_prob": 0.011430188082158566
        },
        {
          "id": "K_B_4.png",
          "label": "K",
          "softmax_prob": 0.027028175070881844
        },
        {
          "id": "K_B_4.png",
          "label": "L",
          "softmax_prob": 0.005879364442080259
        },
        {
          "id": "K_B_4.png",
          "label": "M",
          "softmax_prob": 0.108134426176548
        },
        {
          "id": "K_B_4.png",
          "label": "N",
          "softmax_prob": 0.07675959169864655
        },
        {
          "id": "K_B_4.png",
          "label": "O",
          "softmax_prob": 0.01916869729757309
        },
        {
          "id": "K_B_4.png",
          "label": "P",
          "softmax_prob": 0.006709256675094366
        },
        {
          "id": "K_B_4.png",
          "label": "Q",
          "softmax_prob": 0.003501366591081023
        },
        {
          "id": "K_B_4.png",
          "label": "R",
          "softmax_prob": 0.04995223507285118
        },
        {
          "id": "K_B_4.png",
          "label": "S",
          "softmax_prob": 0.007685333956032991
        },
        {
          "id": "K_B_4.png",
          "label": "T",
          "softmax_prob": 0.019100075587630272
        },
        {
          "id": "K_B_4.png",
          "label": "U",
          "softmax_prob": 0.042648594826459885
        },
        {
          "id": "K_B_4.png",
          "label": "V",
          "softmax_prob": 0.005081376992166042
        },
        {
          "id": "K_B_4.png",
          "label": "W",
          "softmax_prob": 0.0109413405880332
        },
        {
          "id": "K_B_4.png",
          "label": "X",
          "softmax_prob": 0.04131162911653519
        },
        {
          "id": "K_B_4.png",
          "label": "Y",
          "softmax_prob": 0.00558484997600317
        },
        {
          "id": "K_B_4.png",
          "label": "Z",
          "softmax_prob": 0.03248864412307739
        }
      ]
    },
    {
      "id": "K_B_5.png",
      "raws": [
        {
          "id": "K_B_5.png",
          "label": "A",
          "softmax_prob": 0.022239504382014275
        },
        {
          "id": "K_B_5.png",
          "label": "B",
          "softmax_prob": 0.010886243544518948
        },
        {
          "id": "K_B_5.png",
          "label": "C",
          "softmax_prob": 0.10139258950948715
        },
        {
          "id": "K_B_5.png",
          "label": "D",
          "softmax_prob": 0.05205165222287178
        },
        {
          "id": "K_B_5.png",
          "label": "E",
          "softmax_prob": 0.03635403886437416
        },
        {
          "id": "K_B_5.png",
          "label": "F",
          "softmax_prob": 0.03496025130152702
        },
        {
          "id": "K_B_5.png",
          "label": "G",
          "softmax_prob": 0.01712014339864254
        },
        {
          "id": "K_B_5.png",
          "label": "H",
          "softmax_prob": 0.013486267067492008
        },
        {
          "id": "K_B_5.png",
          "label": "I",
          "softmax_prob": 0.26722195744514465
        },
        {
          "id": "K_B_5.png",
          "label": "J",
          "softmax_prob": 0.03862813860177994
        },
        {
          "id": "K_B_5.png",
          "label": "K",
          "softmax_prob": 0.018760543316602707
        },
        {
          "id": "K_B_5.png",
          "label": "L",
          "softmax_prob": 0.02918204478919506
        },
        {
          "id": "K_B_5.png",
          "label": "M",
          "softmax_prob": 0.016946371644735336
        },
        {
          "id": "K_B_5.png",
          "label": "N",
          "softmax_prob": 0.009082379750907421
        },
        {
          "id": "K_B_5.png",
          "label": "O",
          "softmax_prob": 0.06769989430904388
        },
        {
          "id": "K_B_5.png",
          "label": "P",
          "softmax_prob": 0.009531109593808651
        },
        {
          "id": "K_B_5.png",
          "label": "Q",
          "softmax_prob": 0.012831859290599823
        },
        {
          "id": "K_B_5.png",
          "label": "R",
          "softmax_prob": 0.010427284054458141
        },
        {
          "id": "K_B_5.png",
          "label": "S",
          "softmax_prob": 0.03549426048994064
        },
        {
          "id": "K_B_5.png",
          "label": "T",
          "softmax_prob": 0.0427454337477684
        },
        {
          "id": "K_B_5.png",
          "label": "U",
          "softmax_prob": 0.02296574041247368
        },
        {
          "id": "K_B_5.png",
          "label": "V",
          "softmax_prob": 0.017312778159976006
        },
        {
          "id": "K_B_5.png",
          "label": "W",
          "softmax_prob": 0.01395703386515379
        },
        {
          "id": "K_B_5.png",
          "label": "X",
          "softmax_prob": 0.01711888052523136
        },
        {
          "id": "K_B_5.png",
          "label": "Y",
          "softmax_prob": 0.01906980574131012
        },
        {
          "id": "K_B_5.png",
          "label": "Z",
          "softmax_prob": 0.0625336691737175
        }
      ]
    },
    {
      "id": "K_B_6.png",
      "raws": [
        {
          "id": "K_B_6.png",
          "label": "A",
          "softmax_prob": 0.0010350868105888367
        },
        {
          "id": "K_B_6.png",
          "label": "B",
          "softmax_prob": 0.002362698782235384
        },
        {
          "id": "K_B_6.png",
          "label": "C",
          "softmax_prob": 0.010271046310663223
        },
        {
          "id": "K_B_6.png",
          "label": "D",
          "softmax_prob": 0.0013466611271724105
        },
        {
          "id": "K_B_6.png",
          "label": "E",
          "softmax_prob": 0.015851767733693123
        },
        {
          "id": "K_B_6.png",
          "label": "F",
          "softmax_prob": 0.07511229068040848
        },
        {
          "id": "K_B_6.png",
          "label": "G",
          "softmax_prob": 0.00128106155898422
        },
        {
          "id": "K_B_6.png",
          "label": "H",
          "softmax_prob": 0.0017052249750122428
        },
        {
          "id": "K_B_6.png",
          "label": "I",
          "softmax_prob": 0.04143597185611725
        },
        {
          "id": "K_B_6.png",
          "label": "J",
          "softmax_prob": 0.018439505249261856
        },
        {
          "id": "K_B_6.png",
          "label": "K",
          "softmax_prob": 0.010180620476603508
        },
        {
          "id": "K_B_6.png",
          "label": "L",
          "softmax_prob": 0.006704299245029688
        },
        {
          "id": "K_B_6.png",
          "label": "M",
          "softmax_prob": 0.0011669116793200374
        },
        {
          "id": "K_B_6.png",
          "label": "N",
          "softmax_prob": 0.0015264108078554273
        },
        {
          "id": "K_B_6.png",
          "label": "O",
          "softmax_prob": 0.002776753855869174
        },
        {
          "id": "K_B_6.png",
          "label": "P",
          "softmax_prob": 0.004542442504316568
        },
        {
          "id": "K_B_6.png",
          "label": "Q",
          "softmax_prob": 0.0018911226652562618
        },
        {
          "id": "K_B_6.png",
          "label": "R",
          "softmax_prob": 0.007043777033686638
        },
        {
          "id": "K_B_6.png",
          "label": "S",
          "softmax_prob": 0.002088621025905013
        },
        {
          "id": "K_B_6.png",
          "label": "T",
          "softmax_prob": 0.0357605405151844
        },
        {
          "id": "K_B_6.png",
          "label": "U",
          "softmax_prob": 0.0012772043701261282
        },
        {
          "id": "K_B_6.png",
          "label": "V",
          "softmax_prob": 0.00214625452645123
        },
        {
          "id": "K_B_6.png",
          "label": "W",
          "softmax_prob": 0.0012005527969449759
        },
        {
          "id": "K_B_6.png",
          "label": "X",
          "softmax_prob": 0.021551109850406647
        },
        {
          "id": "K_B_6.png",
          "label": "Y",
          "softmax_prob": 0.007704806048423052
        },
        {
          "id": "K_B_6.png",
          "label": "Z",
          "softmax_prob": 0.7235973477363586
        }
      ]
    },
    {
      "id": "K_B_7.png",
      "raws": [
        {
          "id": "K_B_7.png",
          "label": "A",
          "softmax_prob": 5.196455822442658e-05
        },
        {
          "id": "K_B_7.png",
          "label": "B",
          "softmax_prob": 5.572697409661487e-05
        },
        {
          "id": "K_B_7.png",
          "label": "C",
          "softmax_prob": 9.151978883892298e-05
        },
        {
          "id": "K_B_7.png",
          "label": "D",
          "softmax_prob": 5.918024180573411e-05
        },
        {
          "id": "K_B_7.png",
          "label": "E",
          "softmax_prob": 5.470611358759925e-05
        },
        {
          "id": "K_B_7.png",
          "label": "F",
          "softmax_prob": 8.408192661590874e-05
        },
        {
          "id": "K_B_7.png",
          "label": "G",
          "softmax_prob": 0.0002267150703119114
        },
        {
          "id": "K_B_7.png",
          "label": "H",
          "softmax_prob": 9.304323612013832e-05
        },
        {
          "id": "K_B_7.png",
          "label": "I",
          "softmax_prob": 0.00013896865129936486
        },
        {
          "id": "K_B_7.png",
          "label": "J",
          "softmax_prob": 0.0001790939422789961
        },
        {
          "id": "K_B_7.png",
          "label": "K",
          "softmax_prob": 0.00012893257371615618
        },
        {
          "id": "K_B_7.png",
          "label": "L",
          "softmax_prob": 0.997946560382843
        },
        {
          "id": "K_B_7.png",
          "label": "M",
          "softmax_prob": 6.234837201191112e-05
        },
        {
          "id": "K_B_7.png",
          "label": "N",
          "softmax_prob": 5.078195681562647e-05
        },
        {
          "id": "K_B_7.png",
          "label": "O",
          "softmax_prob": 2.5330551579827443e-05
        },
        {
          "id": "K_B_7.png",
          "label": "P",
          "softmax_prob": 0.00013729998318012804
        },
        {
          "id": "K_B_7.png",
          "label": "Q",
          "softmax_prob": 6.475091504398733e-05
        },
        {
          "id": "K_B_7.png",
          "label": "R",
          "softmax_prob": 6.555962318088859e-05
        },
        {
          "id": "K_B_7.png",
          "label": "S",
          "softmax_prob": 5.388889985624701e-05
        },
        {
          "id": "K_B_7.png",
          "label": "T",
          "softmax_prob": 7.610482862219214e-05
        },
        {
          "id": "K_B_7.png",
          "label": "U",
          "softmax_prob": 3.951381950173527e-05
        },
        {
          "id": "K_B_7.png",
          "label": "V",
          "softmax_prob": 6.039047730155289e-05
        },
        {
          "id": "K_B_7.png",
          "label": "W",
          "softmax_prob": 6.384719745256007e-05
        },
        {
          "id": "K_B_7.png",
          "label": "X",
          "softmax_prob": 6.94411646691151e-05
        },
        {
          "id": "K_B_7.png",
          "label": "Y",
          "softmax_prob": 5.190868614590727e-05
        },
        {
          "id": "K_B_7.png",
          "label": "Z",
          "softmax_prob": 6.843802839284763e-05
        }
      ]
    },
    {
      "id": "K_B_8.png",
      "raws": [
        {
          "id": "K_B_8.png",
          "label": "A",
          "softmax_prob": 0.0004782004398293793
        },
        {
          "id": "K_B_8.png",
          "label": "B",
          "softmax_prob": 0.000609122624155134
        },
        {
          "id": "K_B_8.png",
          "label": "C",
          "softmax_prob": 0.0006828271434642375
        },
        {
          "id": "K_B_8.png",
          "label": "D",
          "softmax_prob": 0.0008344658417627215
        },
        {
          "id": "K_B_8.png",
          "label": "E",
          "softmax_prob": 0.00048337591579183936
        },
        {
          "id": "K_B_8.png",
          "label": "F",
          "softmax_prob": 0.0014882538234815001
        },
        {
          "id": "K_B_8.png",
          "label": "G",
          "softmax_prob": 0.0017915039788931608
        },
        {
          "id": "K_B_8.png",
          "label": "H",
          "softmax_prob": 0.001724356901831925
        },
        {
          "id": "K_B_8.png",
          "label": "I",
          "softmax_prob": 0.009466135874390602
        },
        {
          "id": "K_B_8.png",
          "label": "J",
          "softmax_prob": 0.1165194883942604
        },
        {
          "id": "K_B_8.png",
          "label": "K",
          "softmax_prob": 0.0008167275227606297
        },
        {
          "id": "K_B_8.png",
          "label": "L",
          "softmax_prob": 0.8513540625572205
        },
        {
          "id": "K_B_8.png",
          "label": "M",
          "softmax_prob": 0.00050685292808339
        },
        {
          "id": "K_B_8.png",
          "label": "N",
          "softmax_prob": 0.0004743316094391048
        },
        {
          "id": "K_B_8.png",
          "label": "O",
          "softmax_prob": 0.0002854292106349021
        },
        {
          "id": "K_B_8.png",
          "label": "P",
          "softmax_prob": 0.002239287132397294
        },
        {
          "id": "K_B_8.png",
          "label": "Q",
          "softmax_prob": 0.0003761675034184009
        },
        {
          "id": "K_B_8.png",
          "label": "R",
          "softmax_prob": 0.00048415857600048184
        },
        {
          "id": "K_B_8.png",
          "label": "S",
          "softmax_prob": 0.0025555018801242113
        },
        {
          "id": "K_B_8.png",
          "label": "T",
          "softmax_prob": 0.0013100194046273828
        },
        {
          "id": "K_B_8.png",
          "label": "U",
          "softmax_prob": 0.0007141523528844118
        },
        {
          "id": "K_B_8.png",
          "label": "V",
          "softmax_prob": 0.0008553024963475764
        },
        {
          "id": "K_B_8.png",
          "label": "W",
          "softmax_prob": 0.0005607728962786496
        },
        {
          "id": "K_B_8.png",
          "label": "X",
          "softmax_prob": 0.0006669483846053481
        },
        {
          "id": "K_B_8.png",
          "label": "Y",
          "softmax_prob": 0.0016931146383285522
        },
        {
          "id": "K_B_8.png",
          "label": "Z",
          "softmax_prob": 0.0010294498642906547
        }
      ]
    },
    {
      "id": "K_B_9.png",
      "raws": [
        {
          "id": "K_B_9.png",
          "label": "A",
          "softmax_prob": 0.008219683542847633
        },
        {
          "id": "K_B_9.png",
          "label": "B",
          "softmax_prob": 0.012498902156949043
        },
        {
          "id": "K_B_9.png",
          "label": "C",
          "softmax_prob": 0.00795255322009325
        },
        {
          "id": "K_B_9.png",
          "label": "D",
          "softmax_prob": 0.005133954808115959
        },
        {
          "id": "K_B_9.png",
          "label": "E",
          "softmax_prob": 0.01990237459540367
        },
        {
          "id": "K_B_9.png",
          "label": "F",
          "softmax_prob": 0.08541150391101837
        },
        {
          "id": "K_B_9.png",
          "label": "G",
          "softmax_prob": 0.019503997638821602
        },
        {
          "id": "K_B_9.png",
          "label": "H",
          "softmax_prob": 0.3798835277557373
        },
        {
          "id": "K_B_9.png",
          "label": "I",
          "softmax_prob": 0.0365896038711071
        },
        {
          "id": "K_B_9.png",
          "label": "J",
          "softmax_prob": 0.009433314204216003
        },
        {
          "id": "K_B_9.png",
          "label": "K",
          "softmax_prob": 0.004037061240524054
        },
        {
          "id": "K_B_9.png",
          "label": "L",
          "softmax_prob": 0.0035139245446771383
        },
        {
          "id": "K_B_9.png",
          "label": "M",
          "softmax_prob": 0.28456148505210876
        },
        {
          "id": "K_B_9.png",
          "label": "N",
          "softmax_prob": 0.00436654407531023
        },
        {
          "id": "K_B_9.png",
          "label": "O",
          "softmax_prob": 0.01103964727371931
        },
        {
          "id": "K_B_9.png",
          "label": "P",
          "softmax_prob": 0.004779093898832798
        },
        {
          "id": "K_B_9.png",
          "label": "Q",
          "softmax_prob": 0.00677091209217906
        },
        {
          "id": "K_B_9.png",
          "label": "R",
          "softmax_prob": 0.010286498814821243
        },
        {
          "id": "K_B_9.png",
          "label": "S",
          "softmax_prob": 0.003783893072977662
        },
        {
          "id": "K_B_9.png",
          "label": "T",
          "softmax_prob": 0.00270788068883121
        },
        {
          "id": "K_B_9.png",
          "label": "U",
          "softmax_prob": 0.021280715242028236
        },
        {
          "id": "K_B_9.png",
          "label": "V",
          "softmax_prob": 0.004618557170033455
        },
        {
          "id": "K_B_9.png",
          "label": "W",
          "softmax_prob": 0.043629053980112076
        },
        {
          "id": "K_B_9.png",
          "label": "X",
          "softmax_prob": 0.0021945100743323565
        },
        {
          "id": "K_B_9.png",
          "label": "Y",
          "softmax_prob": 0.001280693570151925
        },
        {
          "id": "K_B_9.png",
          "label": "Z",
          "softmax_prob": 0.006620138883590698
        }
      ]
    }
  ]
}