{
  "count": 10,
  "similarityRate": 0.10364490626379848,
  "trials": [
    {
      "id": "TheOrganizersO_L_1.png",
      "label": "L",
      "similarity": 0.0027916382532566786
    },
    {
      "id": "TheOrganizersO_L_10.png",
      "label": "L",
      "similarity": 0.0030458897817879915
    },
    {
      "id": "TheOrganizersO_L_2.png",
      "label": "L",
      "similarity": 0.0028908310923725367
    },
    {
      "id": "TheOrganizersO_L_3.png",
      "label": "L",
      "similarity": 0.002957989228889346
    },
    {
      "id": "TheOrganizersO_L_4.png",
      "label": "L",
      "similarity": 0.9981216788291931
    },
    {
      "id": "TheOrganizersO_L_5.png",
      "label": "L",
      "similarity": 0.0028908310923725367
    },
    {
      "id": "TheOrganizersO_L_6.png",
      "label": "L",
      "similarity": 0.014410950243473053
    },
    {
      "id": "TheOrganizersO_L_7.png",
      "label": "L",
      "similarity": 0.0031089819967746735
    },
    {
      "id": "TheOrganizersO_L_8.png",
      "label": "L",
      "similarity": 0.003149523166939616
    },
    {
      "id": "TheOrganizersO_L_9.png",
      "label": "L",
      "similarity": 0.0030807489529252052
    }
  ],
  "similarities": [
    {
      "id": "TheOrganizersO_L_1.png",
      "raws": [
        {
          "id": "TheOrganizersO_L_1.png",
          "label": "A",
          "softmax_prob": 0.007920700125396252
        },
        {
          "id": "TheOrganizersO_L_1.png",
          "label": "B",
          "softmax_prob": 0.04973772540688515
        },
        {
          "id": "TheOrganizersO_L_1.png",
          "label": "C",
          "softmax_prob": 0.0035481546074151993
        },
        {
          "id": "TheOrganizersO_L_1.png",
          "label": "D",
          "softmax_prob": 0.4415183663368225
        },
        {
          "id": "TheOrganizersO_L_1.png",
          "label": "E",
          "softmax_prob": 0.0024597456213086843
        },
        {
          "id": "TheOrganizersO_L_1.png",
          "label": "F",
          "softmax_prob": 0.0035526971332728863
        },
        {
          "id": "TheOrganizersO_L_1.png",
          "label": "G",
          "softmax_prob": 0.0033808813896030188
        },
        {
          "id": "TheOrganizersO_L_1.png",
          "label": "H",
          "softmax_prob": 0.005288724321871996
        },
        {
          "id": "TheOrganizersO_L_1.png",
          "label": "I",
          "softmax_prob": 0.01595062017440796
        },
        {
          "id": "TheOrganizersO_L_1.png",
          "label": "J",
          "softmax_prob": 0.0025129884015768766
        },
        {
          "id": "TheOrganizersO_L_1.png",
          "label": "K",
          "softmax_prob": 0.0011152345687150955
        },
        {
          "id": "TheOrganizersO_L_1.png",
          "label": "L",
          "softmax_prob": 0.0027916382532566786
        },
        {
          "id": "TheOrganizersO_L_1.png",
          "label": "M",
          "softmax_prob": 0.002800345653668046
        },
        {
          "id": "TheOrganizersO_L_1.png",
          "label": "N",
          "softmax_prob": 0.0009859575657173991
        },
        {
          "id": "TheOrganizersO_L_1.png",
          "label": "O",
          "softmax_prob": 0.4160118103027344
        },
        {
          "id": "TheOrganizersO_L_1.png",
          "label": "P",
          "softmax_prob": 0.006546316668391228
        },
        {
          "id": "TheOrganizersO_L_1.png",
          "label": "Q",
          "softmax_prob": 0.00530314352363348
        },
        {
          "id": "TheOrganizersO_L_1.png",
          "label": "R",
          "softmax_prob": 0.0013787754578515887
        },
        {
          "id": "TheOrganizersO_L_1.png",
          "label": "S",
          "softmax_prob": 0.0046173217706382275
        },
        {
          "id": "TheOrganizersO_L_1.png",
          "label": "T",
          "softmax_prob": 0.0021588746458292007
        },
        {
          "id": "TheOrganizersO_L_1.png",
          "label": "U",
          "softmax_prob": 0.004893106408417225
        },
        {
          "id": "TheOrganizersO_L_1.png",
          "label": "V",
          "softmax_prob": 0.00245264801196754
        },
        {
          "id": "TheOrganizersO_L_1.png",
          "label": "W",
          "softmax_prob": 0.0012498833239078522
        },
        {
          "id": "TheOrganizersO_L_1.png",
          "label": "X",
          "softmax_prob": 0.003106562653556466
        },
        {
          "id": "TheOrganizersO_L_1.png",
          "label": "Y",
          "softmax_prob": 0.003992635291069746
        },
        {
          "id": "TheOrganizersO_L_1.png",
          "label": "Z",
          "softmax_prob": 0.004725123755633831
        }
      ]
    },
    {
      "id": "TheOrganizersO_L_10.png",
      "raws": [
        {
          "id": "TheOrganizersO_L_10.png",
          "label": "A",
          "softmax_prob": 0.008692145347595215
        },
        {
          "id": "TheOrganizersO_L_10.png",
          "label": "B",
          "softmax_prob": 0.05722006782889366
        },
        {
          "id": "TheOrganizersO_L_10.png",
          "label": "C",
          "softmax_prob": 0.0039029126055538654
        },
        {
          "id": "TheOrganizersO_L_10.png",
          "label": "D",
          "softmax_prob": 0.4040605127811432
        },
        {
          "id": "TheOrganizersO_L_10.png",
          "label": "E",
          "softmax_prob": 0.002773882821202278
        },
        {
          "id": "TheOrganizersO_L_10.png",
          "label": "F",
          "softmax_prob": 0.0038374399300664663
        },
        {
          "id": "TheOrganizersO_L_10.png",
          "label": "G",
          "softmax_prob": 0.0038933642208576202
        },
        {
          "id": "TheOrganizersO_L_10.png",
          "label": "H",
          "softmax_prob": 0.00592951662838459
        },
        {
          "id": "TheOrganizersO_L_10.png",
          "label": "I",
          "softmax_prob": 0.017490355297923088
        },
        {
          "id": "TheOrganizersO_L_10.png",
          "label": "J",
          "softmax_prob": 0.002779752481728792
        },
        {
          "id": "TheOrganizersO_L_10.png",
          "label": "K",
          "softmax_prob": 0.0011828468414023519
        },
        {
          "id": "TheOrganizersO_L_10.png",
          "label": "L",
          "softmax_prob": 0.0030458897817879915
        },
        {
          "id": "TheOrganizersO_L_10.png",
          "label": "M",
          "softmax_prob": 0.002925687236711383
        },
        {
          "id": "TheOrganizersO_L_10.png",
          "label": "N",
          "softmax_prob": 0.0010053570149466395
        },
        {
          "id": "TheOrganizersO_L_10.png",
          "label": "O",
          "softmax_prob": 0.4377656877040863
        },
        {
          "id": "TheOrganizersO_L_10.png",
          "label": "P",
          "softmax_prob": 0.00710703432559967
        },
        {
          "id": "TheOrganizersO_L_10.png",
          "label": "Q",
          "softmax_prob": 0.005665627308189869
        },
        {
          "id": "TheOrganizersO_L_10.png",
          "label": "R",
          "softmax_prob": 0.0014913236955180764
        },
        {
          "id": "TheOrganizersO_L_10.png",
          "label": "S",
          "softmax_prob": 0.0051735476590693
        },
        {
          "id": "TheOrganizersO_L_10.png",
          "label": "T",
          "softmax_prob": 0.002319537801668048
        },
        {
          "id": "TheOrganizersO_L_10.png",
          "label": "U",
          "softmax_prob": 0.0048082428984344006
        },
        {
          "id": "TheOrganizersO_L_10.png",
          "label": "V",
          "softmax_prob": 0.0026416766922920942
        },
        {
          "id": "TheOrganizersO_L_10.png",
          "label": "W",
          "softmax_prob": 0.0012786947190761566
        },
        {
          "id": "TheOrganizersO_L_10.png",
          "label": "X",
          "softmax_prob": 0.0032715420238673687
        },
        {
          "id": "TheOrganizersO_L_10.png",
          "label": "Y",
          "softmax_prob": 0.004359188489615917
        },
        {
          "id": "TheOrganizersO_L_10.png",
          "label": "Z",
          "softmax_prob": 0.005378130357712507
        }
      ]
    },
    {
      "id": "TheOrganizersO_L_2.png",
      "raws": [
        {
          "id": "TheOrganizersO_L_2.png",
          "label": "A",
          "softmax_prob": 0.00825199019163847
        },
        {
          "id": "TheOrganizersO_L_2.png",
          "label": "B",
          "softmax_prob": 0.05242539942264557
        },
        {
          "id": "TheOrganizersO_L_2.png",
          "label": "C",
          "softmax_prob": 0.0037138427142053843
        },
        {
          "id": "TheOrganizersO_L_2.png",
          "label": "D",
          "softmax_prob": 0.42771902680397034
        },
        {
          "id": "TheOrganizersO_L_2.png",
          "label": "E",
          "softmax_prob": 0.0026253003161400557
        },
        {
          "id": "TheOrganizersO_L_2.png",
          "label": "F",
          "softmax_prob": 0.003727551782503724
        },
        {
          "id": "TheOrganizersO_L_2.png",
          "label": "G",
          "softmax_prob": 0.00361860659904778
        },
        {
          "id": "TheOrganizersO_L_2.png",
          "label": "H",
          "softmax_prob": 0.005597369745373726
        },
        {
          "id": "TheOrganizersO_L_2.png",
          "label": "I",
          "softmax_prob": 0.0169663205742836
        },
        {
          "id": "TheOrganizersO_L_2.png",
          "label": "J",
          "softmax_prob": 0.002635036129504442
        },
        {
          "id": "TheOrganizersO_L_2.png",
          "label": "K",
          "softmax_prob": 0.001145001733675599
        },
        {
          "id": "TheOrganizersO_L_2.png",
          "label": "L",
          "softmax_prob": 0.0028908310923725367
        },
        {
          "id": "TheOrganizersO_L_2.png",
          "label": "M",
          "softmax_prob": 0.0028741792775690556
        },
        {
          "id": "TheOrganizersO_L_2.png",
          "label": "N",
          "softmax_prob": 0.0010043904185295105
        },
        {
          "id": "TheOrganizersO_L_2.png",
          "label": "O",
          "softmax_prob": 0.42286092042922974
        },
        {
          "id": "TheOrganizersO_L_2.png",
          "label": "P",
          "softmax_prob": 0.006691582500934601
        },
        {
          "id": "TheOrganizersO_L_2.png",
          "label": "Q",
          "softmax_prob": 0.005484823603183031
        },
        {
          "id": "TheOrganizersO_L_2.png",
          "label": "R",
          "softmax_prob": 0.0014295721193775535
        },
        {
          "id": "TheOrganizersO_L_2.png",
          "label": "S",
          "softmax_prob": 0.004847188480198383
        },
        {
          "id": "TheOrganizersO_L_2.png",
          "label": "T",
          "softmax_prob": 0.0022359113208949566
        },
        {
          "id": "TheOrganizersO_L_2.png",
          "label": "U",
          "softmax_prob": 0.004980018362402916
        },
        {
          "id": "TheOrganizersO_L_2.png",
          "label": "V",
          "softmax_prob": 0.0025586404372006655
        },
        {
          "id": "TheOrganizersO_L_2.png",
          "label": "W",
          "softmax_prob": 0.0012848388869315386
        },
        {
          "id": "TheOrganizersO_L_2.png",
          "label": "X",
          "softmax_prob": 0.0032162428833544254
        },
        {
          "id": "TheOrganizersO_L_2.png",
          "label": "Y",
          "softmax_prob": 0.004194281529635191
        },
        {
          "id": "TheOrganizersO_L_2.png",
          "label": "Z",
          "softmax_prob": 0.005021171644330025
        }
      ]
    },
    {
      "id": "TheOrganizersO_L_3.png",
      "raws": [
        {
          "id": "TheOrganizersO_L_3.png",
          "label": "A",
          "softmax_prob": 0.00846378318965435
        },
        {
          "id": "TheOrganizersO_L_3.png",
          "label": "B",
          "softmax_prob": 0.05438661202788353
        },
        {
          "id": "TheOrganizersO_L_3.png",
          "label": "C",
          "softmax_prob": 0.0038252989761531353
        },
        {
          "id": "TheOrganizersO_L_3.png",
          "label": "D",
          "softmax_prob": 0.4184492826461792
        },
        {
          "id": "TheOrganizersO_L_3.png",
          "label": "E",
          "softmax_prob": 0.0027277369517832994
        },
        {
          "id": "TheOrganizersO_L_3.png",
          "label": "F",
          "softmax_prob": 0.0038279974833130836
        },
        {
          "id": "TheOrganizersO_L_3.png",
          "label": "G",
          "softmax_prob": 0.003777290927246213
        },
        {
          "id": "TheOrganizersO_L_3.png",
          "label": "H",
          "softmax_prob": 0.005808420479297638
        },
        {
          "id": "TheOrganizersO_L_3.png",
          "label": "I",
          "softmax_prob": 0.017577258870005608
        },
        {
          "id": "TheOrganizersO_L_3.png",
          "label": "J",
          "softmax_prob": 0.0027044930029660463
        },
        {
          "id": "TheOrganizersO_L_3.png",
          "label": "K",
          "softmax_prob": 0.0011634125839918852
        },
        {
          "id": "TheOrganizersO_L_3.png",
          "label": "L",
          "softmax_prob": 0.002957989228889346
        },
        {
          "id": "TheOrganizersO_L_3.png",
          "label": "M",
          "softmax_prob": 0.0029248956125229597
        },
        {
          "id": "TheOrganizersO_L_3.png",
          "label": "N",
          "softmax_prob": 0.001012513879686594
        },
        {
          "id": "TheOrganizersO_L_3.png",
          "label": "O",
          "softmax_prob": 0.4275456368923187
        },
        {
          "id": "TheOrganizersO_L_3.png",
          "label": "P",
          "softmax_prob": 0.006821195594966412
        },
        {
          "id": "TheOrganizersO_L_3.png",
          "label": "Q",
          "softmax_prob": 0.005586481653153896
        },
        {
          "id": "TheOrganizersO_L_3.png",
          "label": "R",
          "softmax_prob": 0.0014575195964425802
        },
        {
          "id": "TheOrganizersO_L_3.png",
          "label": "S",
          "softmax_prob": 0.004997825715690851
        },
        {
          "id": "TheOrganizersO_L_3.png",
          "label": "T",
          "softmax_prob": 0.00228284765034914
        },
        {
          "id": "TheOrganizersO_L_3.png",
          "label": "U",
          "softmax_prob": 0.005006114020943642
        },
        {
          "id": "TheOrganizersO_L_3.png",
          "label": "V",
          "softmax_prob": 0.002619375241920352
        },
        {
          "id": "TheOrganizersO_L_3.png",
          "label": "W",
          "softmax_prob": 0.0013033548602834344
        },
        {
          "id": "TheOrganizersO_L_3.png",
          "label": "X",
          "softmax_prob": 0.0032700002193450928
        },
        {
          "id": "TheOrganizersO_L_3.png",
          "label": "Y",
          "softmax_prob": 0.00429938780143857
        },
        {
          "id": "TheOrganizersO_L_3.png",
          "label": "Z",
          "softmax_prob": 0.005203251726925373
        }
      ]
    },
    {
      "id": "TheOrganizersO_L_4.png",
      "raws": [
        {
          "id": "TheOrganizersO_L_4.png",
          "label": "A",
          "softmax_prob": 3.9679631299804896e-05
        },
        {
          "id": "TheOrganizersO_L_4.png",
          "label": "B",
          "softmax_prob": 6.116839358583093e-05
        },
        {
          "id": "TheOrganizersO_L_4.png",
          "label": "C",
          "softmax_prob": 0.00011472531332401559
        },
        {
          "id": "TheOrganizersO_L_4.png",
          "label": "D",
          "softmax_prob": 6.0259881138335913e-05
        },
        {
          "id": "TheOrganizersO_L_4.png",
          "label": "E",
          "softmax_prob": 5.0802595069399104e-05
        },
        {
          "id": "TheOrganizersO_L_4.png",
          "label": "F",
          "softmax_prob": 7.810898387106135e-05
        },
        {
          "id": "TheOrganizersO_L_4.png",
          "label": "G",
          "softmax_prob": 0.00011454580817371607
        },
        {
          "id": "TheOrganizersO_L_4.png",
          "label": "H",
          "softmax_prob": 5.219043305260129e-05
        },
        {
          "id": "TheOrganizersO_L_4.png",
          "label": "I",
          "softmax_prob": 0.00015973714471329004
        },
        {
          "id": "TheOrganizersO_L_4.png",
          "label": "J",
          "softmax_prob": 0.00013310069334693253
        },
        {
          "id": "TheOrganizersO_L_4.png",
          "label": "K",
          "softmax_prob": 0.00011811021977337077
        },
        {
          "id": "TheOrganizersO_L_4.png",
          "label": "L",
          "softmax_prob": 0.9981216788291931
        },
        {
          "id": "TheOrganizersO_L_4.png",
          "label": "M",
          "softmax_prob": 6.92635148880072e-05
        },
        {
          "id": "TheOrganizersO_L_4.png",
          "label": "N",
          "softmax_prob": 4.9800884880824015e-05
        },
        {
          "id": "TheOrganizersO_L_4.png",
          "label": "O",
          "softmax_prob": 3.375125379534438e-05
        },
        {
          "id": "TheOrganizersO_L_4.png",
          "label": "P",
          "softmax_prob": 0.00010859768372029066
        },
        {
          "id": "TheOrganizersO_L_4.png",
          "label": "Q",
          "softmax_prob": 5.588748899754137e-05
        },
        {
          "id": "TheOrganizersO_L_4.png",
          "label": "R",
          "softmax_prob": 6.56786432955414e-05
        },
        {
          "id": "TheOrganizersO_L_4.png",
          "label": "S",
          "softmax_prob": 5.198363942326978e-05
        },
        {
          "id": "TheOrganizersO_L_4.png",
          "label": "T",
          "softmax_prob": 8.895400969777256e-05
        },
        {
          "id": "TheOrganizersO_L_4.png",
          "label": "U",
          "softmax_prob": 3.426115290494636e-05
        },
        {
          "id": "TheOrganizersO_L_4.png",
          "label": "V",
          "softmax_prob": 6.458508141804487e-05
        },
        {
          "id": "TheOrganizersO_L_4.png",
          "label": "W",
          "softmax_prob": 5.047290324000642e-05
        },
        {
          "id": "TheOrganizersO_L_4.png",
          "label": "X",
          "softmax_prob": 7.204539724625647e-05
        },
        {
          "id": "TheOrganizersO_L_4.png",
          "label": "Y",
          "softmax_prob": 6.119722092989832e-05
        },
        {
          "id": "TheOrganizersO_L_4.png",
          "label": "Z",
          "softmax_prob": 8.93258475116454e-05
        }
      ]
    },
    {
      "id": "TheOrganizersO_L_5.png",
      "raws": [
        {
          "id": "TheOrganizersO_L_5.png",
          "label": "A",
          "softmax_prob": 0.00825199019163847
        },
        {
          "id": "TheOrganizersO_L_5.png",
          "label": "B",
          "softmax_prob": 0.05242539942264557
        },
        {
          "id": "TheOrganizersO_L_5.png",
          "label": "C",
          "softmax_prob": 0.0037138427142053843
        },
        {
          "id": "TheOrganizersO_L_5.png",
          "label": "D",
          "softmax_prob": 0.42771902680397034
        },
        {
          "id": "TheOrganizersO_L_5.png",
          "label": "E",
          "softmax_prob": 0.0026253003161400557
        },
        {
          "id": "TheOrganizersO_L_5.png",
          "label": "F",
          "softmax_prob": 0.003727551782503724
        },
        {
          "id": "TheOrganizersO_L_5.png",
          "label": "G",
          "softmax_prob": 0.00361860659904778
        },
        {
          "id": "TheOrganizersO_L_5.png",
          "label": "H",
          "softmax_prob": 0.005597369745373726
        },
        {
          "id": "TheOrganizersO_L_5.png",
          "label": "I",
          "softmax_prob": 0.0169663205742836
        },
        {
          "id": "TheOrganizersO_L_5.png",
          "label": "J",
          "softmax_prob": 0.002635036129504442
        },
        {
          "id": "TheOrganizersO_L_5.png",
          "label": "K",
          "softmax_prob": 0.001145001733675599
        },
        {
          "id": "TheOrganizersO_L_5.png",
          "label": "L",
          "softmax_prob": 0.0028908310923725367
        },
        {
          "id": "TheOrganizersO_L_5.png",
          "label": "M",
          "softmax_prob": 0.0028741792775690556
        },
        {
          "id": "TheOrganizersO_L_5.png",
          "label": "N",
          "softmax_prob": 0.0010043904185295105
        },
        {
          "id": "TheOrganizersO_L_5.png",
          "label": "O",
          "softmax_prob": 0.42286092042922974
        },
        {
          "id": "TheOrganizersO_L_5.png",
          "label": "P",
          "softmax_prob": 0.006691582500934601
        },
        {
          "id": "TheOrganizersO_L_5.png",
          "label": "Q",
          "softmax_prob": 0.005484823603183031
        },
        {
          "id": "TheOrganizersO_L_5.png",
          "label": "R",
          "softmax_prob": 0.0014295721193775535
        },
        {
          "id": "TheOrganizersO_L_5.png",
          "label": "S",
          "softmax_prob": 0.004847188480198383
        },
        {
          "id": "TheOrganizersO_L_5.png",
          "label": "T",
          "softmax_prob": 0.0022359113208949566
        },
        {
          "id": "TheOrganizersO_L_5.png",
          "label": "U",
          "softmax_prob": 0.004980018362402916
        },
        {
          "id": "TheOrganizersO_L_5.png",
          "label": "V",
          "softmax_prob": 0.0025586404372006655
        },
        {
          "id": "TheOrganizersO_L_5.png",
          "label": "W",
          "softmax_prob": 0.0012848388869315386
        },
        {
          "id": "TheOrganizersO_L_5.png",
          "label": "X",
          "softmax_prob": 0.0032162428833544254
        },
        {
          "id": "TheOrganizersO_L_5.png",
          "label": "Y",
          "softmax_prob": 0.004194281529635191
        },
        {
          "id": "TheOrganizersO_L_5.png",
          "label": "Z",
          "softmax_prob": 0.005021171644330025
        }
      ]
    },
    {
      "id": "TheOrganizersO_L_6.png",
      "raws": [
        {
          "id": "TheOrganizersO_L_6.png",
          "label": "A",
          "softmax_prob": 0.02345552109181881
        },
        {
          "id": "TheOrganizersO_L_6.png",
          "label": "B",
          "softmax_prob": 0.010543053038418293
        },
        {
          "id": "TheOrganizersO_L_6.png",
          "label": "C",
          "softmax_prob": 0.002420201199129224
        },
        {
          "id": "TheOrganizersO_L_6.png",
          "label": "D",
          "softmax_prob": 0.0075226835906505585
        },
        {
          "id": "TheOrganizersO_L_6.png",
          "label": "E",
          "softmax_prob": 0.002028512302786112
        },
        {
          "id": "TheOrganizersO_L_6.png",
          "label": "F",
          "softmax_prob": 0.32696080207824707
        },
        {
          "id": "TheOrganizersO_L_6.png",
          "label": "G",
          "softmax_prob": 0.0016876772278919816
        },
        {
          "id": "TheOrganizersO_L_6.png",
          "label": "H",
          "softmax_prob": 0.08003925532102585
        },
        {
          "id": "TheOrganizersO_L_6.png",
          "label": "I",
          "softmax_prob": 0.010160455480217934
        },
        {
          "id": "TheOrganizersO_L_6.png",
          "label": "J",
          "softmax_prob": 0.017201339825987816
        },
        {
          "id": "TheOrganizersO_L_6.png",
          "label": "K",
          "softmax_prob": 0.008464678190648556
        },
        {
          "id": "TheOrganizersO_L_6.png",
          "label": "L",
          "softmax_prob": 0.014410950243473053
        },
        {
          "id": "TheOrganizersO_L_6.png",
          "label": "M",
          "softmax_prob": 0.0052825394086539745
        },
        {
          "id": "TheOrganizersO_L_6.png",
          "label": "N",
          "softmax_prob": 0.030412571504712105
        },
        {
          "id": "TheOrganizersO_L_6.png",
          "label": "O",
          "softmax_prob": 0.01157453004270792
        },
        {
          "id": "TheOrganizersO_L_6.png",
          "label": "P",
          "softmax_prob": 0.266816645860672
        },
        {
          "id": "TheOrganizersO_L_6.png",
          "label": "Q",
          "softmax_prob": 0.0039627812802791595
        },
        {
          "id": "TheOrganizersO_L_6.png",
          "label": "R",
          "softmax_prob": 0.00638247188180685
        },
        {
          "id": "TheOrganizersO_L_6.png",
          "label": "S",
          "softmax_prob": 0.01427149586379528
        },
        {
          "id": "TheOrganizersO_L_6.png",
          "label": "T",
          "softmax_prob": 0.09526035189628601
        },
        {
          "id": "TheOrganizersO_L_6.png",
          "label": "U",
          "softmax_prob": 0.003384894458577037
        },
        {
          "id": "TheOrganizersO_L_6.png",
          "label": "V",
          "softmax_prob": 0.006099581718444824
        },
        {
          "id": "TheOrganizersO_L_6.png",
          "label": "W",
          "softmax_prob": 0.0033099872525781393
        },
        {
          "id": "TheOrganizersO_L_6.png",
          "label": "X",
          "softmax_prob": 0.015506930649280548
        },
        {
          "id": "TheOrganizersO_L_6.png",
          "label": "Y",
          "softmax_prob": 0.021900564432144165
        },
        {
          "id": "TheOrganizersO_L_6.png",
          "label": "Z",
          "softmax_prob": 0.010939544066786766
        }
      ]
    },
    {
      "id": "TheOrganizersO_L_7.png",
      "raws": [
        {
          "id": "TheOrganizersO_L_7.png",
          "label": "A",
          "softmax_prob": 0.008857155218720436
        },
        {
          "id": "TheOrganizersO_L_7.png",
          "label": "B",
          "softmax_prob": 0.06013897806406021
        },
        {
          "id": "TheOrganizersO_L_7.png",
          "label": "C",
          "softmax_prob": 0.003930818755179644
        },
        {
          "id": "TheOrganizersO_L_7.png",
          "label": "D",
          "softmax_prob": 0.3964375853538513
        },
        {
          "id": "TheOrganizersO_L_7.png",
          "label": "E",
          "softmax_prob": 0.002828973811119795
        },
        {
          "id": "TheOrganizersO_L_7.png",
          "label": "F",
          "softmax_prob": 0.0038871115539222956
        },
        {
          "id": "TheOrganizersO_L_7.png",
          "label": "G",
          "softmax_prob": 0.00396983465179801
        },
        {
          "id": "TheOrganizersO_L_7.png",
          "label": "H",
          "softmax_prob": 0.006044475361704826
        },
        {
          "id": "TheOrganizersO_L_7.png",
          "label": "I",
          "softmax_prob": 0.017708754166960716
        },
        {
          "id": "TheOrganizersO_L_7.png",
          "label": "J",
          "softmax_prob": 0.002824827330186963
        },
        {
          "id": "TheOrganizersO_L_7.png",
          "label": "K",
          "softmax_prob": 0.0012007273035123944
        },
        {
          "id": "TheOrganizersO_L_7.png",
          "label": "L",
          "softmax_prob": 0.0031089819967746735
        },
        {
          "id": "TheOrganizersO_L_7.png",
          "label": "M",
          "softmax_prob": 0.0029625161550939083
        },
        {
          "id": "TheOrganizersO_L_7.png",
          "label": "N",
          "softmax_prob": 0.001012469525448978
        },
        {
          "id": "TheOrganizersO_L_7.png",
          "label": "O",
          "softmax_prob": 0.4410873055458069
        },
        {
          "id": "TheOrganizersO_L_7.png",
          "label": "P",
          "softmax_prob": 0.0072023821994662285
        },
        {
          "id": "TheOrganizersO_L_7.png",
          "label": "Q",
          "softmax_prob": 0.005662098526954651
        },
        {
          "id": "TheOrganizersO_L_7.png",
          "label": "R",
          "softmax_prob": 0.0015148284146562219
        },
        {
          "id": "TheOrganizersO_L_7.png",
          "label": "S",
          "softmax_prob": 0.005277764517813921
        },
        {
          "id": "TheOrganizersO_L_7.png",
          "label": "T",
          "softmax_prob": 0.0023642044980078936
        },
        {
          "id": "TheOrganizersO_L_7.png",
          "label": "U",
          "softmax_prob": 0.004803234711289406
        },
        {
          "id": "TheOrganizersO_L_7.png",
          "label": "V",
          "softmax_prob": 0.002685175510123372
        },
        {
          "id": "TheOrganizersO_L_7.png",
          "label": "W",
          "softmax_prob": 0.0012859682319685817
        },
        {
          "id": "TheOrganizersO_L_7.png",
          "label": "X",
          "softmax_prob": 0.0032994381617754698
        },
        {
          "id": "TheOrganizersO_L_7.png",
          "label": "Y",
          "softmax_prob": 0.004416666924953461
        },
        {
          "id": "TheOrganizersO_L_7.png",
          "label": "Z",
          "softmax_prob": 0.005487747490406036
        }
      ]
    },
    {
      "id": "TheOrganizersO_L_8.png",
      "raws": [
        {
          "id": "TheOrganizersO_L_8.png",
          "label": "A",
          "softmax_prob": 0.00888294167816639
        },
        {
          "id": "TheOrganizersO_L_8.png",
          "label": "B",
          "softmax_prob": 0.0626700147986412
        },
        {
          "id": "TheOrganizersO_L_8.png",
          "label": "C",
          "softmax_prob": 0.0040792119689285755
        },
        {
          "id": "TheOrganizersO_L_8.png",
          "label": "D",
          "softmax_prob": 0.375194251537323
        },
        {
          "id": "TheOrganizersO_L_8.png",
          "label": "E",
          "softmax_prob": 0.002913361880928278
        },
        {
          "id": "TheOrganizersO_L_8.png",
          "label": "F",
          "softmax_prob": 0.0039221858605742455
        },
        {
          "id": "TheOrganizersO_L_8.png",
          "label": "G",
          "softmax_prob": 0.004197228234261274
        },
        {
          "id": "TheOrganizersO_L_8.png",
          "label": "H",
          "softmax_prob": 0.006171155720949173
        },
        {
          "id": "TheOrganizersO_L_8.png",
          "label": "I",
          "softmax_prob": 0.01774965040385723
        },
        {
          "id": "TheOrganizersO_L_8.png",
          "label": "J",
          "softmax_prob": 0.002900470979511738
        },
        {
          "id": "TheOrganizersO_L_8.png",
          "label": "K",
          "softmax_prob": 0.0012273956090211868
        },
        {
          "id": "TheOrganizersO_L_8.png",
          "label": "L",
          "softmax_prob": 0.003149523166939616
        },
        {
          "id": "TheOrganizersO_L_8.png",
          "label": "M",
          "softmax_prob": 0.00295088067650795
        },
        {
          "id": "TheOrganizersO_L_8.png",
          "label": "N",
          "softmax_prob": 0.0010177188087254763
        },
        {
          "id": "TheOrganizersO_L_8.png",
          "label": "O",
          "softmax_prob": 0.45818302035331726
        },
        {
          "id": "TheOrganizersO_L_8.png",
          "label": "P",
          "softmax_prob": 0.0072176954708993435
        },
        {
          "id": "TheOrganizersO_L_8.png",
          "label": "Q",
          "softmax_prob": 0.005943283438682556
        },
        {
          "id": "TheOrganizersO_L_8.png",
          "label": "R",
          "softmax_prob": 0.0015628784894943237
        },
        {
          "id": "TheOrganizersO_L_8.png",
          "label": "S",
          "softmax_prob": 0.0053703743033111095
        },
        {
          "id": "TheOrganizersO_L_8.png",
          "label": "T",
          "softmax_prob": 0.0024558657314628363
        },
        {
          "id": "TheOrganizersO_L_8.png",
          "label": "U",
          "softmax_prob": 0.004808842670172453
        },
        {
          "id": "TheOrganizersO_L_8.png",
          "label": "V",
          "softmax_prob": 0.002732532797381282
        },
        {
          "id": "TheOrganizersO_L_8.png",
          "label": "W",
          "softmax_prob": 0.0013024272629991174
        },
        {
          "id": "TheOrganizersO_L_8.png",
          "label": "X",
          "softmax_prob": 0.003340810304507613
        },
        {
          "id": "TheOrganizersO_L_8.png",
          "label": "Y",
          "softmax_prob": 0.004481180105358362
        },
        {
          "id": "TheOrganizersO_L_8.png",
          "label": "Z",
          "softmax_prob": 0.005575086921453476
        }
      ]
    },
    {
      "id": "TheOrganizersO_L_9.png",
      "raws": [
        {
          "id": "TheOrganizersO_L_9.png",
          "label": "A",
          "softmax_prob": 0.0087568499147892
        },
        {
          "id": "TheOrganizersO_L_9.png",
          "label": "B",
          "softmax_prob": 0.058498065918684006
        },
        {
          "id": "TheOrganizersO_L_9.png",
          "label": "C",
          "softmax_prob": 0.0039165145717561245
        },
        {
          "id": "TheOrganizersO_L_9.png",
          "label": "D",
          "softmax_prob": 0.4016096889972687
        },
        {
          "id": "TheOrganizersO_L_9.png",
          "label": "E",
          "softmax_prob": 0.002803450683131814
        },
        {
          "id": "TheOrganizersO_L_9.png",
          "label": "F",
          "softmax_prob": 0.00387187534943223
        },
        {
          "id": "TheOrganizersO_L_9.png",
          "label": "G",
          "softmax_prob": 0.003930907696485519
        },
        {
          "id": "TheOrganizersO_L_9.png",
          "label": "H",
          "softmax_prob": 0.005993567407131195
        },
        {
          "id": "TheOrganizersO_L_9.png",
          "label": "I",
          "softmax_prob": 0.017658216878771782
        },
        {
          "id": "TheOrganizersO_L_9.png",
          "label": "J",
          "softmax_prob": 0.002805970376357436
        },
        {
          "id": "TheOrganizersO_L_9.png",
          "label": "K",
          "softmax_prob": 0.0011913488851860166
        },
        {
          "id": "TheOrganizersO_L_9.png",
          "label": "L",
          "softmax_prob": 0.0030807489529252052
        },
        {
          "id": "TheOrganizersO_L_9.png",
          "label": "M",
          "softmax_prob": 0.002948858542367816
        },
        {
          "id": "TheOrganizersO_L_9.png",
          "label": "N",
          "softmax_prob": 0.0010097967460751534
        },
        {
          "id": "TheOrganizersO_L_9.png",
          "label": "O",
          "softmax_prob": 0.43816351890563965
        },
        {
          "id": "TheOrganizersO_L_9.png",
          "label": "P",
          "softmax_prob": 0.007147009484469891
        },
        {
          "id": "TheOrganizersO_L_9.png",
          "label": "Q",
          "softmax_prob": 0.005656743422150612
        },
        {
          "id": "TheOrganizersO_L_9.png",
          "label": "R",
          "softmax_prob": 0.0015006999019533396
        },
        {
          "id": "TheOrganizersO_L_9.png",
          "label": "S",
          "softmax_prob": 0.005219168961048126
        },
        {
          "id": "TheOrganizersO_L_9.png",
          "label": "T",
          "softmax_prob": 0.002338410122320056
        },
        {
          "id": "TheOrganizersO_L_9.png",
          "label": "U",
          "softmax_prob": 0.004824832081794739
        },
        {
          "id": "TheOrganizersO_L_9.png",
          "label": "V",
          "softmax_prob": 0.0026645318139344454
        },
        {
          "id": "TheOrganizersO_L_9.png",
          "label": "W",
          "softmax_prob": 0.0012865985045209527
        },
        {
          "id": "TheOrganizersO_L_9.png",
          "label": "X",
          "softmax_prob": 0.0032886576373130083
        },
        {
          "id": "TheOrganizersO_L_9.png",
          "label": "Y",
          "softmax_prob": 0.004396338947117329
        },
        {
          "id": "TheOrganizersO_L_9.png",
          "label": "Z",
          "softmax_prob": 0.005437645595520735
        }
      ]
    }
  ]
}